{
  "text": {
    " ": 0,
    "h": 2060,
    "o": 3178,
    "l": 2521,
    "a": 605,
    " h": 261,
    "ho": 2119,
    "ol": 3259,
    "la": 2523,
    "a ": 606,
    " ho": 280,
    "hol": 2126,
    "ola": 3261,
    "la ": 2524,
    " hol": 282,
    "hola": 2128,
    "ola ": 3262,
    "b": 995,
    "u": 4423,
    "e": 1491,
    "n": 2906,
    "s": 3966,
    " b": 69,
    "bu": 1085,
    "ue": 4472,
    "en": 1649,
    "no": 3047,
    "os": 3407,
    "s ": 3967,
    " bu": 87,
    "bue": 1086,
    "uen": 4484,
    "eno": 1678,
    "nos": 3058,
    "os ": 3408,
    " bue": 88,
    "buen": 1087,
    "ueno": 4488,
    "enos": 1681,
    "nos ": 3059,
    "d": 1332,
    "í": 4867,
    " d": 134,
    "dí": 1484,
    "ía": 4869,
    "as": 895,
    " dí": 171,
    "día": 1485,
    "ías": 4873,
    "as ": 896,
    " día": 172,
    "días": 1487,
    "ías ": 4874,
    "na": 2908,
    "ena": 1651,
    "nas": 2929,
    "uena": 4486,
    "enas": 1655,
    "nas ": 2930,
    "t": 4219,
    "r": 3637,
    " t": 531,
    "ta": 4221,
    "ar": 854,
    "rd": 3688,
    "de": 1359,
    "es": 1788,
    " ta": 532,
    "tar": 4250,
    "ard": 862,
    "rde": 3692,
    "des": 1395,
    "es ": 1789,
    " tar": 536,
    "tard": 4252,
    "arde": 863,
    "rdes": 3696,
    "des ": 1396,
    "c": 1093,
    " n": 384,
    "oc": 3196,
    "ch": 1162,
    "he": 2099,
    " no": 395,
    "noc": 3049,
    "och": 3203,
    "che": 1172,
    "hes": 2106,
    " noc": 397,
    "noch": 3050,
    "oche": 3204,
    "ches": 1174,
    "hes ": 2107,
    "q": 3618,
    "é": 4853,
    " q": 463,
    "qu": 3619,
    "ué": 4646,
    "é ": 4854,
    " qu": 464,
    "qué": 3633,
    "ué ": 4647,
    " qué": 467,
    "qué ": 3634,
    "al": 722,
    "l ": 2522,
    "tal": 4234,
    "al ": 723,
    " tal": 533,
    "tal ": 4235,
    " s": 495,
    "sa": 3968,
    "lu": 2704,
    "ud": 4457,
    "do": 1454,
    " sa": 496,
    "sal": 3982,
    "alu": 763,
    "lud": 2709,
    "udo": 4468,
    "dos": 1467,
    " sal": 498,
    "salu": 3984,
    "alud": 765,
    "ludo": 2712,
    "udos": 4471,
    "dos ": 1468,
    "y": 4772,
    "ey": 1883,
    "y ": 4773,
    " he": 271,
    "hey": 2108,
    "ey ": 1884,
    " hey": 275,
    "hey ": 2109,
    " e": 175,
    " ey": 217,
    " ey ": 218,
    "bo": 1059,
    "ot": 3423,
    "t ": 4220,
    " bo": 80,
    "bot": 1068,
    "ot ": 3424,
    " bot": 84,
    "bot ": 1069,
    "m": 2741,
    "i": 2143,
    "g": 1985,
    " a": 1,
    "am": 766,
    "mi": 2812,
    "ig": 2254,
    "go": 2017,
    "o ": 3179,
    " am": 35,
    "ami": 780,
    "mig": 2820,
    "igo": 2263,
    "go ": 2018,
    " ami": 37,
    "amig": 782,
    "migo": 2821,
    "igo ": 2264,
    " o": 409,
    "on": 3311,
    "nd": 2954,
    "da": 1334,
    " on": 419,
    "ond": 3322,
    "nda": 2955,
    "da ": 1335,
    " ond": 420,
    "onda": 3323,
    "nda ": 2956,
    "á": 4821,
    " m": 348,
    "má": 2892,
    "ás": 4843,
    " má": 377,
    "más": 2895,
    "ás ": 4844,
    " más": 379,
    "más ": 2896,
    "ó": 4918,
    " c": 92,
    "có": 1329,
    "óm": 4923,
    "mo": 2843,
    " có": 132,
    "cóm": 1330,
    "ómo": 4926,
    "mo ": 2844,
    " cóm": 133,
    "cómo": 1331,
    "ómo ": 4927,
    "v": 4658,
    " v": 566,
    "va": 4659,
    " va": 567,
    "vas": 4672,
    " vas": 571,
    "vas ": 4673,
    "st": 4159,
    "tá": 4407,
    " es": 200,
    "est": 1833,
    "stá": 4192,
    "tás": 4409,
    " est": 205,
    "está": 1840,
    "stás": 4194,
    "tás ": 4410,
    "li": 2615,
    "i ": 2144,
    "oli": 3269,
    "li ": 2616,
    "holi": 2129,
    "oli ": 3270,
    "it": 2430,
    "lit": 2637,
    "ita": 2431,
    "ta ": 4222,
    "olit": 3271,
    "lita": 2638,
    "ita ": 2432,
    "bi": 1026,
    "ie": 2216,
    "nv": 3153,
    "ve": 4676,
    "ni": 3014,
    "id": 2199,
    " bi": 75,
    "bie": 1032,
    "ien": 2227,
    "env": 1696,
    "nve": 3156,
    "ven": 4686,
    "eni": 1675,
    "nid": 3020,
    "ido": 2213,
    "do ": 1455,
    " bie": 76,
    "bien": 1033,
    "ienv": 2234,
    "enve": 1697,
    "nven": 3157,
    "veni": 4688,
    "enid": 1676,
    "nido": 3021,
    "ido ": 2214,
    "ha": 2061,
    "ay": 960,
    " ha": 262,
    "hay": 2090,
    "ay ": 961,
    " hay": 269,
    "hay ": 2091,
    "n ": 2907,
    "en ": 1650,
    "uen ": 4485,
    "ía ": 4870,
    "día ": 1486,
    "f": 1897,
    "z": 4790,
    " f": 219,
    "fe": 1913,
    "el": 1599,
    "iz": 2462,
    "z ": 4791,
    " fe": 226,
    "fel": 1917,
    "eli": 1612,
    "liz": 2639,
    "iz ": 2463,
    " fel": 227,
    "feli": 1918,
    "eliz": 1615,
    "liz ": 2640,
    "di": 1410,
    "to": 4338,
    "udi": 4464,
    "dit": 1448,
    "ito": 2443,
    "to ": 4339,
    "ludi": 2711,
    "udit": 4467,
    "dito": 1449,
    "ito ": 2444,
    "co": 1229,
    "or": 3369,
    "ia": 2145,
    "le": 2578,
    " co": 112,
    "cor": 1253,
    "ord": 3379,
    "rdi": 3697,
    "dia": 1411,
    "ial": 2151,
    "ale": 733,
    "les": 2602,
    " cor": 117,
    "cord": 1256,
    "ordi": 3382,
    "rdia": 3698,
    "dial": 1412,
    "iale": 2153,
    "ales": 736,
    "les ": 2603,
    "te": 4263,
    "e ": 1492,
    " te": 537,
    "te ": 4264,
    " te ": 538,
    "va ": 4660,
    " va ": 568,
    "fu": 1965,
    " fu": 239,
    "fue": 1966,
    "ue ": 4473,
    " fue": 240,
    "fue ": 1967,
    "ac": 635,
    "ce": 1138,
    "hac": 2066,
    "ace": 638,
    "ces": 1157,
    " hac": 265,
    "hace": 2067,
    "aces": 642,
    "ces ": 1158,
    "ma": 2742,
    "an": 790,
    "ne": 2972,
    "ec": 1514,
    "ci": 1179,
    "is": 2398,
    "ama": 767,
    "man": 2758,
    "ane": 803,
    "nec": 2974,
    "eci": 1529,
    "cis": 1214,
    "ist": 2424,
    "ste": 4167,
    " ama": 36,
    "aman": 771,
    "mane": 2761,
    "anec": 804,
    "neci": 2976,
    "ecis": 1537,
    "cist": 1216,
    "iste": 2425,
    "ste ": 4168,
    " an": 38,
    "and": 800,
    "das": 1352,
    " and": 39,
    "anda": 801,
    "ndas": 2957,
    "das ": 1353,
    "se": 4017,
    " se": 499,
    "se ": 4018,
    " se ": 500,
    "ic": 2180,
    " di": 151,
    "dic": 1415,
    "ice": 2186,
    "ce ": 1139,
    " dic": 153,
    "dice": 1417,
    "ice ": 2187,
    "cu": 1294,
    "nt": 3101,
    " cu": 125,
    "cue": 1302,
    "ent": 1687,
    "nta": 3102,
    "tas": 4257,
    " cue": 127,
    "cuen": 1304,
    "uent": 4489,
    "enta": 1688,
    "ntas": 3110,
    "tas ": 4258,
    " de": 139,
    "de ": 1360,
    " de ": 140,
    "nu": 3138,
    "ev": 1854,
    "vo": 4722,
    " nu": 401,
    "nue": 3145,
    "uev": 4502,
    "evo": 1865,
    "vo ": 4723,
    " nue": 403,
    "nuev": 3146,
    "uevo": 4504,
    "evo ": 1866,
    "aa": 607,
    "laa": 2525,
    "aaa": 609,
    "aa ": 608,
    "olaa": 3263,
    "laaa": 2526,
    "aaa ": 610,
    "mu": 2883,
    "uy": 4636,
    " mu": 372,
    "muy": 2890,
    "uy ": 4637,
    " muy": 376,
    "muy ": 2891,
    "na ": 2909,
    "ena ": 1652,
    "j": 2480,
    " j": 311,
    "jo": 2502,
    "rn": 3833,
    "ad": 664,
    " jo": 314,
    "jor": 2504,
    "orn": 3397,
    "rna": 3834,
    "nad": 2914,
    "ada": 666,
    " jor": 315,
    "jorn": 2507,
    "orna": 3398,
    "rnad": 3835,
    "nada": 2915,
    "ada ": 667,
    "om": 3284,
    "nz": 3159,
    "zo": 4810,
    "com": 1238,
    "omi": 3294,
    "mie": 2817,
    "enz": 1698,
    "nzo": 3163,
    "zo ": 4811,
    " com": 115,
    "comi": 1240,
    "omie": 3296,
    "mien": 2819,
    "ienz": 2235,
    "enzo": 1700,
    "nzo ": 3164,
    "at": 926,
    "tb": 4260,
    " ch": 105,
    "cha": 1163,
    "hat": 2084,
    "atb": 931,
    "tbo": 4261,
    " cha": 106,
    "chat": 1169,
    "hatb": 2086,
    "atbo": 932,
    "tbot": 4262,
    "od": 3216,
    " to": 548,
    "tod": 4344,
    "odo": 3224,
    " tod": 549,
    "todo": 4346,
    "odo ": 3225,
    "á ": 4822,
    "tá ": 4408,
    "stá ": 4193,
    "p": 3456,
    " p": 431,
    "pu": 3604,
    " pu": 459,
    "pue": 3605,
    "ues": 4499,
    " pue": 460,
    "pues": 3607,
    "ues ": 4500,
    "pa": 3457,
    " pa": 432,
    "pas": 3479,
    "asa": 897,
    "sa ": 3969,
    " pas": 435,
    "pasa": 3480,
    "asa ": 898,
    " u": 560,
    "un": 4562,
    " un": 561,
    "un ": 4563,
    " un ": 562,
    "udo ": 4469,
    "so": 4113,
    "eso": 1820,
    "so ": 4114,
    " eso": 203,
    "eso ": 1821,
    "k": 2517,
    "cr": 1265,
    "ra": 3639,
    "ck": 1219,
    "k ": 2518,
    " cr": 119,
    "cra": 1266,
    "rac": 3644,
    "ack": 649,
    "ck ": 1220,
    " cra": 120,
    "crac": 1267,
    "rack": 3646,
    "ack ": 650,
    "áq": 4840,
    "ui": 4508,
    "in": 2306,
    "máq": 2893,
    "áqu": 4841,
    "qui": 3626,
    "uin": 4520,
    "ina": 2308,
    " máq": 378,
    "máqu": 2894,
    "áqui": 4842,
    "quin": 3629,
    "uina": 4521,
    "ina ": 2309,
    "hu": 2135,
    "ub": 4439,
    " hu": 285,
    "hub": 2136,
    "ubo": 4442,
    "bo ": 1060,
    " hub": 286,
    "hubo": 2137,
    "ubo ": 4443,
    "uda": 4458,
    "dan": 1344,
    "ndo": 2965,
    "luda": 2710,
    "udan": 4461,
    "dand": 1346,
    "ando": 802,
    "ndo ": 2966,
    "tr": 4363,
    " ot": 427,
    "otr": 3436,
    "tra": 4364,
    "ra ": 3640,
    " otr": 428,
    "otra": 3437,
    "tra ": 4365,
    "ez": 1885,
    " ve": 573,
    "vez": 4700,
    "ez ": 1886,
    " vez": 579,
    "vez ": 4701,
    "er": 1730,
    "ri": 3776,
    "que": 3620,
    "uer": 4493,
    "eri": 1753,
    "rid": 3786,
    " que": 465,
    "quer": 3624,
    "ueri": 4496,
    "erid": 1755,
    "rido": 3788,
    "ti": 4294,
    "im": 2284,
    "sti": 4173,
    "tim": 4316,
    "ima": 2285,
    "mad": 2749,
    "ado": 680,
    "esti": 1836,
    "stim": 4176,
    "tima": 4317,
    "imad": 2287,
    "mado": 2751,
    "ado ": 681,
    "si": 4058,
    " as": 53,
    "asi": 909,
    "sis": 4088,
    "ten": 4272,
    "nte": 3111,
    " asi": 55,
    "asis": 913,
    "sist": 4090,
    "sten": 4170,
    "tent": 4279,
    "ente": 1689,
    "nte ": 3112,
    " g": 249,
    "gu": 2039,
    "us": 4593,
    " gu": 258,
    "gus": 2053,
    "ust": 4608,
    "sto": 4179,
    " gus": 259,
    "gust": 2054,
    "usto": 4612,
    "sto ": 4180,
    "rt": 3901,
    "dar": 1347,
    "art": 889,
    "rte": 3908,
    "udar": 4462,
    "dart": 1351,
    "arte": 890,
    "rte ": 3909,
    "ió": 2475,
    "ós": 4934,
    " ad": 13,
    "adi": 677,
    "dió": 1452,
    "iós": 2478,
    "ós ": 4935,
    " adi": 15,
    "adió": 679,
    "diós": 1453,
    "iós ": 2479,
    "has": 2081,
    "ast": 918,
    "sta": 4160,
    " has": 268,
    "hast": 2083,
    "asta": 919,
    "sta ": 4161,
    " l": 319,
    "eg": 1573,
    " lu": 343,
    "lue": 2713,
    "ueg": 4478,
    "ego": 1577,
    " lue": 345,
    "lueg": 2714,
    "uego": 4479,
    "ego ": 1578,
    " nos": 399,
    "em": 1626,
    "vem": 4684,
    "emo": 1638,
    "mos": 2856,
    " vem": 576,
    "vemo": 4685,
    "emos": 1641,
    "mos ": 2857,
    "ao": 832,
    "hao": 2076,
    "ao ": 833,
    "chao": 1166,
    "hao ": 2077,
    "pr": 3570,
    "ro": 3839,
    " pr": 451,
    "pro": 3584,
    "ron": 3857,
    "ont": 3349,
    "nto": 3125,
    " pro": 454,
    "pron": 3592,
    "ront": 3860,
    "onto": 3352,
    "nto ": 3126,
    "me": 2792,
    " me": 355,
    "me ": 2793,
    " me ": 356,
    "ng": 3005,
    "eng": 1672,
    "ngo": 3009,
    " ten": 541,
    "teng": 4276,
    "engo": 1674,
    "ngo ": 3010,
    "que ": 3621,
    " i": 288,
    "ir": 2376,
    "r ": 3638,
    " ir": 307,
    "ir ": 2377,
    " ir ": 308,
    "by": 1090,
    "ye": 4778,
    " by": 90,
    "bye": 1091,
    "ye ": 4779,
    " bye": 91,
    "bye ": 1092,
    "ñ": 4897,
    "añ": 982,
    "ña": 4898,
    " ma": 349,
    "mañ": 2780,
    "aña": 983,
    "ñan": 4901,
    "ana": 792,
    " mañ": 354,
    "maña": 2781,
    "añan": 985,
    "ñana": 4902,
    "ana ": 793,
    "ga": 1986,
    "nga": 3006,
    "gas": 1996,
    "enga": 1673,
    "ngas": 3008,
    "gas ": 1997,
    " la": 320,
    " la ": 321,
    "x": 4742,
    "ró": 3959,
    "óx": 4938,
    "xi": 4752,
    "pró": 3595,
    "róx": 3964,
    "óxi": 4939,
    "xim": 4753,
    "ma ": 2743,
    " pró": 455,
    "próx": 3596,
    "róxi": 3965,
    "óxim": 4940,
    "xima": 4754,
    "ima ": 2286,
    "uí": 4652,
    "íd": 4875,
    "cuí": 1324,
    "uíd": 4656,
    "ída": 4876,
    "dat": 1355,
    "ate": 933,
    " cuí": 131,
    "cuíd": 1325,
    "uída": 4657,
    "ídat": 4878,
    "date": 1356,
    "ate ": 934,
    "sc": 3997,
    "ca": 1094,
    "ns": 3071,
    "esc": 1797,
    "sca": 3998,
    "can": 1111,
    "ans": 818,
    "nse": 3081,
    "ses": 4043,
    " des": 149,
    "desc": 1398,
    "esca": 1798,
    "scan": 3999,
    "cans": 1113,
    "anse": 820,
    "nses": 3084,
    "ses ": 4044,
    "ab": 611,
    "bl": 1046,
    "hab": 2063,
    "abl": 623,
    "bla": 1047,
    "lam": 2537,
    "amo": 784,
    " hab": 264,
    "habl": 2065,
    "abla": 624,
    "blam": 1049,
    "lamo": 2540,
    "amos": 785,
    "sp": 4137,
    "és": 4865,
    "esp": 1824,
    "spu": 4153,
    "pué": 3610,
    "ués": 4650,
    "és ": 4866,
    "desp": 1403,
    "espu": 1830,
    "spué": 4155,
    "pués": 3611,
    "ués ": 4651,
    "una": 4564,
    " una": 563,
    "una ": 4565,
    "he ": 2100,
    "che ": 1173,
    "au": 943,
    "u ": 4424,
    "hau": 2087,
    "au ": 944,
    "chau": 1170,
    "hau ": 2088,
    "nc": 2931,
    " en": 188,
    "ton": 4352,
    "onc": 3319,
    "nce": 2935,
    " ent": 193,
    "ento": 1691,
    "nton": 3127,
    "tonc": 4353,
    "once": 3320,
    "nces": 2939,
    "ya": 4774,
    "vay": 4674,
    "aya": 962,
    "ya ": 4775,
    " vay": 572,
    "vaya": 4675,
    "aya ": 963,
    "ien ": 2228,
    " el": 182,
    "el ": 1600,
    " el ": 183,
    "imo": 2298,
    "ximo": 4755,
    "imo ": 2299,
    "at ": 927,
    "hat ": 2085,
    "rde ": 3693,
    "nsa": 3072,
    "ansa": 819,
    "nsa ": 3073,
    "ea": 1493,
    "vea": 4678,
    "eam": 1501,
    " vea": 574,
    "veam": 4679,
    "eamo": 1502,
    "pi": 3519,
    "spi": 4145,
    "pid": 3522,
    "espi": 1827,
    "spid": 4146,
    "pido": 3523,
    "té": 4411,
    "sté": 4195,
    "tés": 4413,
    "esté": 1841,
    "stés": 4197,
    "tés ": 4414,
    "den": 1382,
    "ntr": 3129,
    "tro": 4382,
    "ro ": 3840,
    " den": 147,
    "dent": 1385,
    "entr": 1692,
    "ntro": 3132,
    "tro ": 4383,
    "po": 3546,
    " po": 446,
    "poc": 3548,
    "oco": 3209,
    "co ": 1230,
    " poc": 447,
    "poco": 3549,
    "oco ": 3210,
    " y": 593,
    " ya": 595,
    " ya ": 596,
    "oy": 3444,
    " vo": 585,
    "voy": 4732,
    "oy ": 3445,
    " voy": 587,
    "voy ": 4733,
    "rr": 3873,
    " ci": 107,
    "cie": 1195,
    "ier": 2236,
    "err": 1770,
    "rro": 3887,
    " cie": 108,
    "cier": 1197,
    "ierr": 2239,
    "erro": 1773,
    "rro ": 3888,
    "ón": 4928,
    "esi": 1811,
    "sió": 4099,
    "ión": 2476,
    "ón ": 4929,
    " ses": 507,
    "sesi": 4045,
    "esió": 1817,
    "sión": 4100,
    "ión ": 2477,
    "fi": 1923,
    " fi": 228,
    "fin": 1934,
    "in ": 2307,
    " fin": 229,
    "fin ": 1935,
    "del": 1375,
    " del": 145,
    "del ": 1376,
    "rm": 3817,
    "nó": 3171,
    "ó ": 4919,
    "ter": 4282,
    "erm": 1758,
    "rmi": 3826,
    "min": 2827,
    "inó": 2351,
    "nó ": 3172,
    " ter": 542,
    "term": 4285,
    "ermi": 1760,
    "rmin": 3828,
    "minó": 2830,
    "inó ": 2352,
    "por": 3559,
    "or ": 3370,
    " por": 449,
    "por ": 3560,
    "hoy": 2133,
    " hoy": 284,
    "hoy ": 2134,
    "pl": 3536,
    " pl": 444,
    "pla": 3537,
    "lac": 2531,
    "cer": 1152,
    "er ": 1731,
    " pla": 445,
    "plac": 3538,
    "lace": 2532,
    "acer": 641,
    "cer ": 1153,
    "ee": 1563,
    " le": 326,
    "lee": 2586,
    "eem": 1564,
    " lee": 328,
    "leem": 2587,
    "eemo": 1565,
    "enc": 1656,
    "nco": 2948,
    "con": 1243,
    "ram": 3658,
    " enc": 190,
    "enco": 1660,
    "ncon": 2950,
    "cont": 1251,
    "ontr": 3353,
    "ntra": 3130,
    "tram": 4370,
    "ramo": 3661,
    "ase": 903,
    "pase": 3481,
    "ases": 906,
    "otro": 3438,
    "gr": 2025,
    " gr": 255,
    "gra": 2026,
    "aci": 643,
    "cia": 1180,
    "ias": 2167,
    " gra": 256,
    "grac": 2027,
    "raci": 3645,
    "acia": 644,
    "cias": 1186,
    "ias ": 2168,
    " y ": 594,
    " r": 468,
    "re": 3703,
    "et": 1842,
    " re": 472,
    "ret": 3758,
    "eti": 1850,
    "tir": 4328,
    "iro": 2387,
    " ret": 482,
    "reti": 3760,
    "etir": 1852,
    "tiro": 4331,
    "iro ": 2388,
    "aq": 849,
    "í ": 4868,
    " aq": 48,
    "aqu": 850,
    "quí": 3635,
    "uí ": 4653,
    " aqu": 49,
    "aquí": 853,
    "quí ": 3636,
    "ll": 2642,
    " ll": 334,
    "lle": 2648,
    "leg": 2588,
    " lle": 336,
    "lleg": 2649,
    "lego": 2590,
    "seg": 4025,
    "egu": 1582,
    "gui": 2043,
    "uim": 4518,
    " seg": 502,
    "segu": 4026,
    "egui": 1583,
    "guim": 2044,
    "uimo": 4519,
    "imos": 2300,
    "no ": 3048,
    "eno ": 1679,
    "ai": 706,
    "hai": 2069,
    "ait": 711,
    "chai": 1164,
    "hait": 2070,
    "aito": 712,
    "ej": 1586,
    "dej": 1372,
    "ejo": 1595,
    "jo ": 2503,
    " dej": 144,
    "dejo": 1374,
    "ejo ": 1596,
    " ce": 102,
    "rra": 3874,
    "rar": 3669,
    "ar ": 855,
    " cer": 104,
    "cerr": 1155,
    "erra": 1771,
    "rrar": 3877,
    "rar ": 3670,
    "ct": 1282,
    "sco": 4001,
    "one": 3326,
    "ect": 1542,
    "cto": 1289,
    "esco": 1799,
    "scon": 4003,
    "cone": 1247,
    "onec": 3327,
    "nect": 2977,
    "ecto": 1545,
    "cto ": 1290,
    " a ": 2,
    "sar": 3991,
    "nsar": 3079,
    "sar ": 3992,
    "mp": 2862,
    " si": 509,
    "sie": 4070,
    "iem": 2225,
    "emp": 1642,
    "mpr": 2878,
    "pre": 3571,
    "re ": 3704,
    " sie": 511,
    "siem": 4072,
    "iemp": 2226,
    "empr": 1646,
    "mpre": 2879,
    "pre ": 3572,
    "ag": 689,
    "zc": 4801,
    " ag": 19,
    "agr": 697,
    "rad": 3648,
    "ade": 670,
    "dez": 1407,
    "ezc": 1890,
    "zco": 4802,
    " agr": 21,
    "agra": 698,
    "grad": 2028,
    "rade": 3649,
    "adez": 676,
    "dezc": 1409,
    "ezco": 1891,
    "zco ": 4803,
    "uc": 4444,
    "muc": 2884,
    "uch": 4449,
    "cho": 1177,
    "ho ": 2120,
    " muc": 373,
    "much": 2885,
    "ucho": 4451,
    "cho ": 1178,
    "esta": 1834,
    "star": 4166,
    "tar ": 4251,
    "ah": 700,
    "hí": 2141,
    " ah": 22,
    "ahí": 704,
    "hí ": 2142,
    " ahí": 24,
    "ahí ": 705,
    "dec": 1365,
    "cid": 1191,
    "adec": 672,
    "deci": 1367,
    "ecid": 1532,
    "cido": 1194,
    "lo": 2664,
    " lo": 338,
    "lo ": 2665,
    " lo ": 339,
    "az": 969,
    "zó": 4818,
    "ora": 3371,
    "raz": 3679,
    "azó": 977,
    "zón": 4819,
    "cora": 1255,
    "oraz": 3376,
    "razó": 3681,
    "azón": 978,
    "zón ": 4820,
    "il": 2271,
    " mi": 362,
    "mil": 2823,
    "il ": 2272,
    " mil": 365,
    "mil ": 2824,
    "nf": 2990,
    " in": 296,
    "inf": 2321,
    "nfi": 2995,
    "ini": 2329,
    "nit": 3031,
    " inf": 300,
    "infi": 2324,
    "nfin": 2997,
    "fini": 1937,
    "init": 2330,
    "nita": 3032,
    "itas": 2437,
    " et": 206,
    "ete": 1847,
    "ern": 1762,
    "nam": 2924,
    "ame": 777,
    "men": 2804,
    " ete": 207,
    "eter": 1849,
    "tern": 4286,
    "erna": 1763,
    "rnam": 3836,
    "name": 2925,
    "amen": 779,
    "ment": 2807,
    "d ": 1333,
    "ver": 4692,
    "erd": 1742,
    "rda": 3689,
    "dad": 1338,
    "ad ": 665,
    " ver": 578,
    "verd": 4695,
    "erda": 1743,
    "rdad": 3690,
    "dad ": 1339,
    "tu": 4394,
    " tu": 555,
    "tu ": 4395,
    " tu ": 556,
    "ap": 834,
    "yo": 4782,
    " ap": 43,
    "apo": 843,
    "poy": 3568,
    "oyo": 3448,
    "yo ": 4783,
    " apo": 46,
    "apoy": 844,
    "poyo": 3569,
    "oyo ": 3449,
    "end": 1662,
    "nde": 2958,
    "der": 1390,
    "rme": 3822,
    "nten": 3115,
    "tend": 4274,
    "ende": 1663,
    "nder": 2962,
    "derm": 1393,
    "erme": 1759,
    "rme ": 3823,
    "scu": 4008,
    "cuc": 1300,
    "har": 2078,
    "arm": 882,
    " esc": 202,
    "escu": 1801,
    "scuc": 4009,
    "cuch": 1301,
    "ucha": 4450,
    "char": 1167,
    "harm": 2080,
    "arme": 883,
    "chas": 1168,
    "has ": 2082,
    " ti": 544,
    "tie": 4305,
    "mpo": 2873,
    "po ": 3547,
    " tie": 546,
    "tiem": 4306,
    "empo": 1645,
    "mpo ": 2874,
    "mab": 2744,
    "ble": 1051,
    "le ": 2579,
    "amab": 769,
    "mabl": 2745,
    "able": 625,
    "ble ": 1052,
    "tus": 4404,
    "us ": 4594,
    " tus": 557,
    "tus ": 4405,
    "br": 1071,
    "pal": 3465,
    "ala": 724,
    "lab": 2527,
    "abr": 630,
    "bra": 1072,
    "ras": 3672,
    " pal": 433,
    "pala": 3467,
    "alab": 725,
    "labr": 2530,
    "abra": 631,
    "bras": 1073,
    "ras ": 3673,
    "res": 3749,
    "spo": 4148,
    "pon": 3555,
    " res": 481,
    "resp": 3757,
    "espo": 1828,
    "spon": 4149,
    "pond": 3556,
    "onde": 3324,
    "bon": 1063,
    "oni": 3334,
    " bon": 82,
    "boni": 1064,
    "onit": 3336,
    "nito": 3034,
    "ij": 2268,
    "ji": 2499,
    "dij": 1431,
    "iji": 2269,
    "jis": 2500,
    " dij": 157,
    "diji": 1432,
    "ijis": 2270,
    "jist": 2501,
    "yu": 4784,
    " ay": 64,
    "ayu": 965,
    "yud": 4785,
    " ayu": 65,
    "ayud": 966,
    "yuda": 4786,
    "udas": 4463,
    "dast": 1354,
    "aste": 920,
    "uda ": 4459,
    "io": 2355,
    " em": 185,
    "moc": 2845,
    "oci": 3205,
    "cio": 1206,
    "ion": 2357,
    "ona": 3313,
    "nal": 2919,
    " emo": 186,
    "emoc": 1639,
    "moci": 2846,
    "ocio": 3208,
    "cion": 1208,
    "iona": 2358,
    "onal": 3316,
    "nal ": 2920,
    "ib": 2171,
    "dis": 1440,
    "isp": 2422,
    "nib": 3015,
    "ibl": 2178,
    " dis": 160,
    "disp": 1446,
    "ispo": 2423,
    "poni": 3557,
    "onib": 3335,
    "nibl": 3016,
    "ible": 2179,
    " ac": 7,
    "aco": 652,
    "omp": 3303,
    "mpa": 2863,
    "pañ": 3485,
    "ñar": 4903,
    " aco": 10,
    "acom": 654,
    "comp": 1242,
    "ompa": 3304,
    "mpañ": 2865,
    "paña": 3486,
    "añar": 986,
    "ñarm": 4904,
    "apr": 845,
    "rec": 3714,
    "io ": 2356,
    " apr": 47,
    "apre": 846,
    "prec": 3573,
    "reci": 3717,
    "ecio": 1535,
    "cio ": 1207,
    "sien": 4073,
    "ient": 2233,
    "ant": 822,
    "tem": 4268,
    "ema": 1627,
    "ano": 814,
    " ant": 42,
    "ante": 824,
    "ntem": 3114,
    "tema": 4269,
    "eman": 1630,
    "mano": 2763,
    "ano ": 815,
    "ren": 3735,
    "ens": 1682,
    "nsi": 3085,
    "ompr": 3307,
    "pren": 3576,
    "rens": 3739,
    "ensi": 1684,
    "nsió": 3091,
    "toy": 4361,
    "esto": 1837,
    "stoy": 4183,
    "toy ": 4362,
    "nti": 3118,
    "tig": 4310,
    " con": 116,
    "onti": 3351,
    "ntig": 3120,
    "tigo": 4312,
    "ons": 3343,
    "sej": 4027,
    "cons": 1250,
    "onse": 3345,
    "nsej": 3083,
    "sejo": 4028,
    "tó": 4418,
    "nca": 2932,
    "ntó": 3136,
    "tó ": 4419,
    "enca": 1657,
    "ncan": 2934,
    "cant": 1114,
    "antó": 827,
    "ntó ": 3137,
    "spue": 4154,
    "uest": 4501,
    " er": 198,
    "ere": 1747,
    " ere": 199,
    "eres": 1749,
    "res ": 3750,
    " at": 57,
    " ate": 59,
    "aten": 935,
    "nci": 2940,
    "ció": 1217,
    "tenc": 4273,
    "enci": 1659,
    "nció": 2947,
    "ción": 1218,
    "ló": 2738,
    "ill": 2279,
    "lló": 2654,
    "lón": 2739,
    "mill": 2826,
    "illó": 2281,
    "llón": 2655,
    "lón ": 2740,
    "eo": 1701,
    "up": 4574,
    "reo": 3741,
    "eoc": 1703,
    "ocu": 3214,
    "cup": 1313,
    "upa": 4575,
    "par": 3473,
    " pre": 452,
    "preo": 3577,
    "reoc": 3743,
    "eocu": 1704,
    "ocup": 3215,
    "cupa": 1314,
    "upar": 4578,
    "part": 3478,
    " no ": 396,
    "be": 1013,
    "sab": 3970,
    "abe": 616,
    "bes": 1022,
    " sab": 497,
    "sabe": 3971,
    "abes": 618,
    "bes ": 1023,
    "uá": 4641,
    "án": 4830,
    "cuá": 1319,
    "uán": 4644,
    "ánt": 4835,
    " cuá": 129,
    "cuán": 1321,
    "uánt": 4645,
    "ánto": 4836,
    "hi": 2110,
    " hi": 276,
    "hic": 2111,
    "ici": 2188,
    " hic": 277,
    "hici": 2112,
    "icis": 2193,
    "sen": 4031,
    " sen": 504,
    "sent": 4034,
    "enti": 1690,
    "ntir": 3124,
    "tir ": 4329,
    "mej": 2798,
    " mej": 358,
    "mejo": 2799,
    "ejor": 1597,
    "jor ": 2505,
    "val": 4666,
    "alo": 752,
    "lor": 2675,
    "oro": 3400,
    " val": 570,
    "valo": 4667,
    "alor": 753,
    "loro": 2678,
    "oro ": 3401,
    "ser": 4040,
    " ser": 506,
    "ser ": 4041,
    "tan": 4243,
    "an ": 791,
    " tan": 534,
    "tan ": 4244,
    "cl": 1223,
    " cl": 109,
    "cla": 1224,
    "lar": 2550,
    "aro": 884,
    " cla": 110,
    "clar": 1225,
    "laro": 2558,
    "aro ": 885,
    "ba": 996,
    " ba": 70,
    "bas": 1006,
    " bas": 72,
    "bast": 1007,
    "stan": 4165,
    "tant": 4247,
    "ex": 1867,
    "xp": 4759,
    " ex": 210,
    "exp": 1876,
    "xpl": 4762,
    "pli": 3544,
    "lic": 2623,
    "ica": 2181,
    "car": 1118,
    " exp": 215,
    "expl": 1878,
    "xpli": 4763,
    "plic": 3545,
    "lica": 2624,
    "icar": 2185,
    "carm": 1122,
    " al": 27,
    " al ": 28,
    "pe": 3491,
    " pe": 436,
    "pen": 3499,
    "ndi": 2963,
    "die": 1422,
    " pen": 439,
    "pend": 3500,
    "endi": 1664,
    "ndie": 2964,
    "dien": 1424,
    "guí": 2055,
    "uía": 4654,
    " guí": 260,
    "guía": 2056,
    "uía ": 4655,
    " ne": 387,
    "ece": 1520,
    "sit": 4091,
    "tab": 4223,
    "aba": 612,
    "ba ": 997,
    " nec": 388,
    "nece": 2975,
    "eces": 1524,
    "cesi": 1160,
    "esit": 1815,
    "sita": 4092,
    "itab": 2433,
    "taba": 4224,
    "aba ": 613,
    "ñí": 4913,
    "añí": 990,
    "ñía": 4914,
    "pañí": 3487,
    "añía": 991,
    "ñía ": 4915,
    "ú": 4941,
    " ú": 600,
    "út": 4957,
    " út": 603,
    "úti": 4958,
    "til": 4313,
    " úti": 604,
    "útil": 4959,
    "til ": 4314,
    "vi": 4702,
    "ua": 4425,
    " vi": 580,
    "vir": 4711,
    "irt": 2393,
    "rtu": 3916,
    "tua": 4396,
    "ual": 4430,
    " vir": 582,
    "virt": 4712,
    "irtu": 2395,
    "rtua": 3917,
    "tual": 4398,
    "ual ": 4431,
    "ál": 4826,
    "uál": 4642,
    "ál ": 4827,
    "cuál": 1320,
    "uál ": 4643,
    " es ": 201,
    "mb": 2782,
    "nom": 3056,
    "omb": 3288,
    "mbr": 2790,
    "bre": 1074,
    " nom": 398,
    "nomb": 3057,
    "ombr": 3289,
    "mbre": 2791,
    "bre ": 1075,
    "dim": 1433,
    "ime": 2291,
    " dim": 158,
    "dime": 1434,
    "ime ": 2292,
    "lla": 2643,
    "mas": 2772,
    " lla": 335,
    "llam": 2645,
    "lama": 2538,
    "amas": 773,
    "mas ": 2773,
    " ia": 289,
    "ia ": 2146,
    " ia ": 290,
    "ip": 2366,
    "tip": 4326,
    "ipo": 2373,
    " tip": 547,
    "tipo": 4327,
    "ipo ": 2374,
    "fun": 1972,
    "unc": 4566,
    " fun": 243,
    "func": 1973,
    "unci": 4568,
    "rea": 3705,
    "eal": 1497,
    " rea": 473,
    "real": 3708,
    "eal ": 1498,
    "cre": 1269,
    "ear": 1503,
    "on ": 3312,
    " cre": 121,
    "crea": 1270,
    "rear": 3709,
    "earo": 1504,
    "aron": 886,
    "ron ": 3858,
    "aj": 713,
    " tr": 552,
    "rab": 3641,
    "baj": 1000,
    "ajo": 718,
    " tra": 553,
    "trab": 4366,
    "raba": 3642,
    "abaj": 614,
    "bajo": 1002,
    "ajo ": 719,
    "ed": 1551,
    "ued": 4474,
    "ede": 1554,
    "pued": 3606,
    "uede": 4476,
    "edes": 1557,
    "onta": 3350,
    "ntar": 3109,
    "tarm": 4255,
    "ob": 3183,
    " so": 517,
    "sob": 4115,
    "obr": 3192,
    " sob": 518,
    "sobr": 4116,
    "obre": 3193,
    "ti ": 4295,
    " ti ": 545,
    "og": 3234,
    "rog": 3849,
    "ogr": 3239,
    "prog": 3589,
    "rogr": 3850,
    "ogra": 3240,
    "gram": 2029,
    "rama": 3659,
    "ama ": 768,
    "hec": 2101,
    "ech": 1525,
    " hec": 273,
    "hech": 2102,
    "echo": 1528,
    "con ": 1244,
    "ge": 2000,
    "int": 2342,
    "tel": 4265,
    "lig": 2629,
    "ige": 2257,
    "gen": 2001,
    " int": 304,
    "inte": 2343,
    "ntel": 3113,
    "teli": 4266,
    "elig": 1613,
    "lige": 2630,
    "igen": 2258,
    "genc": 2002,
    "ncia": 2941,
    "cia ": 1181,
    "if": 2248,
    " ar": 50,
    "rti": 3911,
    "tif": 4308,
    "ifi": 2251,
    "fic": 1926,
    " art": 52,
    "arti": 891,
    "rtif": 3913,
    "tifi": 4309,
    "ific": 2252,
    "fici": 1928,
    "icia": 2189,
    "cial": 1184,
    "ial ": 2152,
    "ono": 3337,
    "cim": 1202,
    "imi": 2294,
    "tos": 4356,
    "cono": 1249,
    "onoc": 3339,
    "noci": 3051,
    "ocim": 3207,
    "cimi": 1203,
    "imie": 2296,
    "ntos": 3128,
    "tos ": 4357,
    "ene": 1666,
    "nes": 2988,
    "tien": 4307,
    "iene": 2231,
    "enes": 1669,
    "nes ": 2989,
    " ro": 486,
    "rol": 3851,
    "ol ": 3260,
    " rol": 488,
    "rol ": 3852,
    "are": 865,
    "eas": 1505,
    "tare": 4253,
    "area": 866,
    "reas": 3710,
    "eas ": 1506,
    "gent": 2004,
    "eb": 1509,
    "rí": 3950,
    "deb": 1363,
    "ebe": 1512,
    "ber": 1018,
    "erí": 1785,
    "ría": 3951,
    " deb": 141,
    "debe": 1364,
    "eber": 1513,
    "berí": 1021,
    "ería": 1786,
    "ría ": 3952,
    " us": 564,
    "usa": 4595,
    " usa": 565,
    "usar": 4596,
    "sart": 3994,
    "ié": 2472,
    "én": 4861,
    "uié": 4531,
    "ién": 2473,
    "én ": 4862,
    " qui": 466,
    "quié": 3632,
    "uién": 4532,
    "ién ": 2474,
    "eñ": 1892,
    "ñó": 4916,
    "ise": 2403,
    "señ": 4049,
    "eñó": 1895,
    "ñó ": 4917,
    "dise": 1442,
    "iseñ": 2404,
    "señó": 4050,
    "eñó ": 1896,
    "cart": 1123,
    "of": 3229,
    "fr": 1952,
    " of": 413,
    "ofr": 3230,
    "fre": 1953,
    " ofr": 414,
    "ofre": 3231,
    "frec": 1954,
    "rece": 3715,
    "ecer": 1523,
    "cerm": 1154,
    "op": 3356,
    "pó": 3615,
    "rop": 3861,
    "opó": 3364,
    "pós": 3616,
    "ósi": 4936,
    "prop": 3593,
    "ropó": 3864,
    "opós": 3365,
    "pósi": 3617,
    "ósit": 4937,
    "sito": 4094,
    "rob": 3841,
    "obo": 3190,
    " rob": 487,
    "robo": 3843,
    "obot": 3191,
    "mó": 2904,
    "amó": 788,
    "mó ": 2905,
    "ramó": 3662,
    "amó ": 789,
    "dar ": 1348,
    "cué": 1322,
    "uén": 4648,
    "ént": 4863,
    "tam": 4240,
    " cué": 130,
    "cuén": 1323,
    "uént": 4649,
    "énta": 4864,
    "ntam": 3107,
    "tame": 4241,
    "ame ": 778,
    " sis": 515,
    "stem": 4169,
    "ema ": 1628,
    "fui": 1968,
    "uis": 4524,
    " fui": 241,
    "fuis": 1969,
    "uist": 4525,
    "ead": 1495,
    "read": 3707,
    "eado": 1496,
    "ace ": 639,
    "dif": 1426,
    "ife": 2249,
    "fer": 1921,
    " dif": 155,
    "dife": 1427,
    "ifer": 2250,
    "fere": 1922,
    "eren": 1748,
    "rent": 3740,
    "ara": 856,
    " par": 434,
    "para": 3475,
    "ara ": 857,
    "mar": 2766,
    "amar": 772,
    "maro": 2771,
    "spe": 4140,
    "pec": 3492,
    "ali": 740,
    "lid": 2625,
    "ida": 2200,
    " esp": 204,
    "espe": 1826,
    "spec": 4141,
    "peci": 3494,
    "ecia": 1530,
    "iali": 2154,
    "alid": 741,
    "lida": 2626,
    "idad": 2202,
    "ncio": 2945,
    "ione": 2359,
    "ones": 3328,
    "las": 2559,
    " las": 324,
    "las ": 2560,
    "rs": 3890,
    "per": 3505,
    "ers": 1774,
    "rso": 3899,
    "son": 4128,
    " per": 440,
    "pers": 3509,
    "erso": 1778,
    "rson": 3900,
    "sona": 4130,
    "onas": 3318,
    "darm": 1350,
    "fo": 1945,
    "nfo": 2999,
    "for": 1950,
    "orm": 3392,
    "rma": 3818,
    "mac": 2746,
    "info": 2325,
    "nfor": 3000,
    "form": 1951,
    "orma": 3393,
    "rmac": 3819,
    "maci": 2748,
    "ació": 648,
    "ja": 2481,
    "nej": 2980,
    "eja": 1587,
    "jas": 2492,
    " man": 351,
    "anej": 805,
    "neja": 2981,
    "ejas": 1592,
    "jas ": 2493,
    " en ": 189,
    "tre": 4375,
    "ntre": 3131,
    "tren": 4377,
    "rena": 3736,
    "enad": 1653,
    "nado": 2918,
    "onv": 3354,
    "rsa": 3891,
    "conv": 1252,
    "onve": 3355,
    "nver": 3158,
    "vers": 4699,
    "ersa": 1775,
    "rsar": 3893,
    "cir": 1212,
    " dec": 142,
    "ecir": 1536,
    "cir ": 1213,
    "roy": 3868,
    "oye": 3446,
    "yec": 4780,
    "proy": 3594,
    "roye": 3869,
    "oyec": 3447,
    "yect": 4781,
    "scr": 4005,
    "cri": 1273,
    "rib": 3783,
    "ibi": 2174,
    "bir": 1041,
    "escr": 1800,
    "scri": 4007,
    "crib": 1274,
    "ribi": 3784,
    "ibir": 2177,
    "birt": 1042,
    "irte": 2394,
    "xa": 4743,
    "exa": 1868,
    "xac": 4744,
    "act": 655,
    "cta": 1283,
    " exa": 211,
    "exac": 1869,
    "xact": 4745,
    "acta": 656,
    "ctam": 1285,
    "ea ": 1494,
    "rea ": 3706,
    "pri": 3580,
    "rin": 3796,
    "inc": 2315,
    "cip": 1209,
    "ipa": 2367,
    " pri": 453,
    "prin": 3582,
    "rinc": 3797,
    "inci": 2316,
    "ncip": 2946,
    "cipa": 1210,
    "ipal": 2368,
    "pal ": 3466,
    "ese": 1804,
    "pres": 3579,
    "rese": 3753,
    "esen": 1806,
    "irí": 2396,
    "birí": 1043,
    "iría": 2397,
    "rías": 3953,
    "clas": 1226,
    "lase": 2561,
    "ase ": 904,
    "tri": 4380,
    "ris": 3803,
    " tri": 554,
    "tris": 4381,
    "rist": 3805,
    "úl": 4947,
    "lt": 2695,
    " úl": 601,
    "últ": 4948,
    "lti": 2700,
    "mam": 2756,
    " últ": 602,
    "últi": 4949,
    "ltim": 2701,
    "imam": 2289,
    "mame": 2757,
    "sio": 4085,
    "ios": 2363,
    "oso": 3417,
    " ans": 41,
    "ansi": 821,
    "nsio": 3090,
    "sios": 4087,
    "ioso": 2365,
    "oso ": 3418,
    "irr": 2389,
    "rri": 3884,
    "rit": 3806,
    " irr": 310,
    "irri": 2392,
    "rrit": 3886,
    "rito": 3809,
    "fa": 1898,
    " fa": 220,
    "fac": 1899,
    "cil": 1198,
    "ili": 2276,
    " fac": 221,
    "faci": 1900,
    "acil": 646,
    "cili": 1199,
    "ilid": 2278,
    "edo": 1561,
    "uedo": 4477,
    "edo ": 1562,
    "trol": 4384,
    "rola": 3853,
    "olar": 3265,
    "lar ": 2551,
    "mi ": 2813,
    " mi ": 363,
    "ied": 2218,
    "eda": 1552,
    "nsie": 3088,
    "sied": 4071,
    "ieda": 2219,
    "edad": 1553,
    "sin": 4083,
    " sin": 514,
    "sin ": 4084,
    "za": 4792,
    "era": 1732,
    "ran": 3663,
    "anz": 828,
    "nza": 3160,
    "za ": 4793,
    "sper": 4144,
    "pera": 3506,
    "eran": 1738,
    "ranz": 3668,
    "anza": 829,
    "nza ": 3161,
    " ca": 93,
    "cam": 1108,
    "amb": 774,
    "mbi": 2783,
    "bio": 1037,
    " cam": 96,
    "camb": 1109,
    "ambi": 775,
    "mbio": 2786,
    "bios": 1038,
    "ios ": 2364,
    "um": 4545,
    "hum": 2138,
    "umo": 4557,
    "mor": 2853,
    " hum": 287,
    "humo": 2140,
    "umor": 4559,
    "mor ": 2854,
    "nst": 3096,
    "tes": 4288,
    "onst": 3347,
    "nsta": 3097,
    "ntes": 3117,
    "tes ": 4289,
    "cí": 1326,
    "ío": 4887,
    "vac": 4661,
    "ací": 662,
    "cío": 1327,
    "ío ": 4888,
    " vac": 569,
    "vací": 4663,
    "acío": 663,
    "cío ": 1328,
    "ep": 1711,
    "dep": 1388,
    "epr": 1723,
    "rim": 3793,
    "mid": 2814,
    " dep": 148,
    "depr": 1389,
    "epri": 1725,
    "prim": 3581,
    "rimi": 3795,
    "imid": 2295,
    "mido": 2816,
    "sd": 4014,
    "esd": 1802,
    "sde": 4015,
    "desd": 1399,
    "esde": 1803,
    "sde ": 4016,
    "sem": 4029,
    " sem": 503,
    "sema": 4030,
    "mana": 2759,
    "anas": 795,
    "ru": 3918,
    " ab": 3,
    "bru": 1077,
    "rum": 3925,
    "uma": 4546,
    " abr": 5,
    "abru": 632,
    "brum": 1078,
    "ruma": 3926,
    "umad": 4548,
    "mis": 2833,
    "is ": 2399,
    " mis": 366,
    "mis ": 2834,
    " ev": 208,
    "evi": 1861,
    "vit": 4717,
    " evi": 209,
    "evit": 1864,
    "vita": 4718,
    "itar": 2436,
    "irm": 2383,
    "tirm": 4330,
    "irme": 2385,
    "ul": 4533,
    "lp": 2681,
    "cul": 1309,
    "ulp": 4539,
    "lpa": 2682,
    "pab": 3458,
    " cul": 128,
    "culp": 1311,
    "ulpa": 4540,
    "lpab": 2683,
    "pabl": 3459,
    "inv": 2349,
    "nva": 3154,
    "vad": 4664,
    " inv": 306,
    "inva": 2350,
    "nvad": 3155,
    "vade": 4665,
    "ade ": 671,
    "tez": 4292,
    "eza": 1887,
    "stez": 4172,
    "teza": 4293,
    "eza ": 1888,
    "rof": 3847,
    "ofu": 3232,
    "und": 4569,
    "prof": 3588,
    "rofu": 3848,
    "ofun": 3233,
    "fund": 1974,
    "unda": 4570,
    " ra": 469,
    " raz": 471,
    "apa": 835,
    " apa": 44,
    "apar": 838,
    "pare": 3476,
    "aren": 869,
    " mie": 364,
    "mied": 2818,
    "iedo": 2220,
    "irra": 2390,
    "rrac": 3875,
    "acio": 647,
    "enu": 1694,
    "nud": 3143,
    " men": 361,
    "menu": 2808,
    "enud": 1695,
    "nudo": 3144,
    " do": 162,
    "dom": 1458,
    " dom": 164,
    "domi": 1460,
    "omin": 3297,
    "mina": 2828,
    "ang": 808,
    "ngu": 3011,
    "tia": 4296,
    " ang": 40,
    "angu": 810,
    "ngus": 3013,
    "usti": 4611,
    "stia": 4174,
    "tia ": 4297,
    "cua": 1295,
    "uan": 4435,
    " cua": 126,
    "cuan": 1299,
    "uand": 4436,
    " pi": 442,
    "pie": 3524,
    "nso": 3092,
    " pie": 443,
    "pien": 3526,
    "iens": 2232,
    "enso": 1685,
    "nso ": 3093,
    "ut": 4616,
    "ur": 4583,
    "fut": 1977,
    "utu": 4631,
    "tur": 4401,
    "uro": 4589,
    " fut": 244,
    "futu": 1978,
    "utur": 4632,
    "turo": 4403,
    "uro ": 4590,
    " ep": 194,
    "epi": 1719,
    "pis": 3532,
    "iso": 2417,
    "sod": 4119,
    "odi": 3222,
    "dio": 1435,
    " epi": 195,
    "epis": 1720,
    "piso": 3533,
    "isod": 2420,
    "sodi": 4120,
    "odio": 3223,
    "dios": 1437,
    "pá": 3612,
    " pá": 461,
    "pán": 3613,
    "áni": 4833,
    "nic": 3017,
    "ico": 2194,
    " pán": 462,
    "páni": 3614,
    "ánic": 4834,
    "nico": 3019,
    "ico ": 2195,
    " fr": 235,
    "ecu": 1547,
    " fre": 236,
    "recu": 3720,
    "ecue": 1549,
    "ef": 1566,
    "ind": 2318,
    "def": 1369,
    "efe": 1567,
    "fen": 1919,
    " ind": 299,
    "inde": 2319,
    "ndef": 2960,
    "defe": 1370,
    "efen": 1569,
    "fens": 1920,
    "itu": 2446,
    "uac": 4426,
    " sit": 516,
    "situ": 4095,
    "itua": 2447,
    "tuac": 4397,
    "uaci": 4427,
    "ncu": 2952,
    "encu": 1661,
    "ncue": 2953,
    "egr": 1580,
    "grí": 2037,
    " ale": 30,
    "aleg": 734,
    "legr": 2591,
    "egrí": 1581,
    "gría": 2038,
    " na": 385,
    " nad": 386,
    "xpe": 4760,
    "expe": 1877,
    "xper": 4761,
    "peri": 3508,
    "erim": 1757,
    "rime": 3794,
    "imen": 2293,
    "fru": 1960,
    "rus": 3929,
    "str": 4184,
    " fru": 237,
    "frus": 1961,
    "rust": 3931,
    "ustr": 4613,
    "stra": 4185,
    "trac": 4367,
    "haz": 2092,
    "aza": 970,
    "zad": 4794,
    " rec": 474,
    "rech": 3716,
    "echa": 1526,
    "chaz": 1171,
    "haza": 2093,
    "azad": 971,
    "zado": 4796,
    "odos": 3226,
    "ata": 928,
    "taq": 4248,
    " ata": 58,
    "ataq": 929,
    "taqu": 4249,
    "aque": 851,
    "ques": 3625,
    "lan": 2541,
    "llan": 2646,
    "lant": 2547,
    "anto": 826,
    "iv": 2448,
    " mo": 367,
    "mot": 2858,
    "oti": 3434,
    "tiv": 4334,
    "ivo": 2458,
    " mot": 370,
    "moti": 2859,
    "otiv": 3435,
    "tivo": 4337,
    "ivo ": 2459,
    "sac": 3974,
    "sens": 4033,
    "ensa": 1683,
    "nsac": 3075,
    "saci": 3975,
    "sol": 4121,
    "ole": 3266,
    "led": 2584,
    " sol": 520,
    "sole": 4122,
    "oled": 3267,
    "leda": 2585,
    "nq": 3068,
    " au": 60,
    "aun": 949,
    "unq": 4572,
    "nqu": 3069,
    " aun": 62,
    "aunq": 950,
    "unqu": 4573,
    "nque": 3070,
    "té ": 4412,
    "sté ": 4196,
    "ñad": 4899,
    "añad": 984,
    "ñado": 4900,
    "ü": 4960,
    "rg": 3767,
    "gü": 2057,
    "üe": 4961,
    "erg": 1750,
    "rgü": 3774,
    "güe": 2058,
    "üen": 4962,
    "verg": 4696,
    "ergü": 1752,
    "rgüe": 3775,
    "güen": 2059,
    "üenz": 4963,
    "enza": 1699,
    "mí": 2902,
    " mí": 382,
    "mí ": 2903,
    " mí ": 383,
    "sm": 4106,
    "ism": 2414,
    "smo": 4111,
    "mism": 2835,
    "ismo": 2416,
    "smo ": 4112,
    "ins": 2338,
    "gur": 2050,
    "uri": 4586,
    " ins": 303,
    "inse": 2339,
    "nseg": 3082,
    "egur": 1585,
    "guri": 2051,
    "urid": 4587,
    "rida": 3787,
    "soc": 4117,
    " soc": 519,
    "soci": 4118,
    "ocia": 3206,
    "lí": 2731,
    "mel": 2800,
    "ela": 1601,
    "anc": 796,
    "col": 1236,
    "olí": 3282,
    "lía": 2732,
    " mel": 359,
    "mela": 2801,
    "elan": 1606,
    "lanc": 2543,
    "anco": 799,
    "ncol": 2949,
    "colí": 1237,
    "olía": 3283,
    "lía ": 2733,
    "ja ": 2482,
    "deja": 1373,
    "eja ": 1588,
    "sf": 4051,
    "isf": 2405,
    "sfr": 4052,
    "rut": 3932,
    "uta": 4617,
    "disf": 1443,
    "isfr": 2406,
    "sfru": 4054,
    "frut": 1962,
    "ruta": 3933,
    "utar": 4621,
    "ntim": 3122,
    "timi": 4318,
    "haci": 2068,
    "han": 2073,
    " han": 267,
    "han ": 2074,
    "her": 2103,
    " her": 274,
    "heri": 2105,
    "lm": 2656,
    "alm": 749,
    "lme": 2659,
    "nalm": 2923,
    "alme": 751,
    "lmen": 2660,
    "xh": 4749,
    "exh": 1872,
    "xha": 4750,
    "aus": 951,
    " exh": 213,
    "exha": 1873,
    "xhau": 4751,
    "haus": 2089,
    "aust": 952,
    "jar": 2490,
    "ejar": 1591,
    "jar ": 2491,
    "abi": 620,
    "bil": 1035,
    "rita": 3807,
    "tabi": 4225,
    "abil": 621,
    "bili": 1036,
    "lg": 2610,
    "gi": 2007,
    "ost": 3421,
    "alg": 737,
    "lgi": 2611,
    "gia": 2008,
    "nost": 3061,
    "osta": 3422,
    "stal": 4163,
    "talg": 4237,
    "algi": 738,
    "lgia": 2612,
    "gia ": 2009,
    "pos": 3563,
    "mpos": 2876,
    "pos ": 3564,
    "ore": 3383,
    "jore": 2506,
    "ores": 3384,
    "dese": 1400,
    "eses": 1808,
    "sesp": 4046,
    "oj": 3253,
    "noj": 3054,
    "ojo": 3254,
    " eno": 192,
    "enoj": 1680,
    "nojo": 3055,
    "ojo ": 3255,
    "arr": 887,
    "rre": 3878,
    "reb": 3712,
    "eba": 1510,
    "bat": 1008,
    "ato": 939,
    " arr": 51,
    "arre": 888,
    "rreb": 3880,
    "reba": 3713,
    "ebat": 1511,
    "bato": 1009,
    "atos": 940,
    "nale": 2921,
    " im": 293,
    "imp": 2301,
    "red": 3721,
    "cib": 1187,
    " imp": 295,
    "impr": 2305,
    "pred": 3574,
    "rede": 3722,
    "edec": 1556,
    "ecib": 1531,
    "cibl": 1188,
    "bles": 1054,
    "bia": 1027,
    "mbia": 2784,
    "bia ": 1028,
    "dr": 1469,
    "rá": 3942,
    " dr": 166,
    "drá": 1470,
    "rás": 3945,
    "ást": 4845,
    "tic": 4298,
    " drá": 167,
    "drás": 1471,
    "rást": 3946,
    "ásti": 4846,
    "stic": 4175,
    "tica": 4299,
    "icam": 2184,
    "came": 1110,
    "vu": 4734,
    "ln": 2661,
    " vu": 588,
    "vul": 4737,
    "uln": 4537,
    "lne": 2662,
    "ner": 2984,
    " vul": 590,
    "vuln": 4738,
    "ulne": 4538,
    "lner": 2663,
    "nera": 2986,
    "erab": 1734,
    "rabl": 3643,
    "sig": 4076,
    "onsi": 3346,
    "nsig": 3089,
    "sigo": 4078,
    "ntu": 3134,
    "usi": 4602,
    "sia": 4060,
    "asm": 914,
    "entu": 1693,
    "ntus": 3135,
    "tusi": 4406,
    "usia": 4603,
    "sias": 4062,
    "iasm": 2170,
    "asmo": 915,
    "tí": 4415,
    "pat": 3483,
    "atí": 941,
    "tía": 4416,
    "apat": 840,
    "patí": 3484,
    "atía": 942,
    "tía ": 4417,
    "erac": 1735,
    "eme": 1634,
    "teme": 4271,
    "emen": 1635,
    "pad": 3462,
    "upad": 4576,
    "pado": 3464,
    "su": 4198,
    " su": 523,
    "sup": 4210,
    "upe": 4579,
    " sup": 527,
    "supe": 4211,
    "uper": 4580,
    "erar": 1739,
    "este": 1835,
    "du": 1474,
    " du": 168,
    "due": 1479,
    "uel": 4480,
    "elo": 1618,
    " due": 170,
    "duel": 1480,
    "uelo": 4482,
    "elo ": 1619,
    "onf": 3329,
    "fia": 1924,
    "ian": 2158,
    "conf": 1248,
    "onfi": 3330,
    "nfia": 2996,
    "fian": 1925,
    "ianz": 2160,
    "pes": 3512,
    "sim": 4080,
    " pes": 441,
    "pesi": 3513,
    "esim": 1812,
    "simi": 4081,
    "imis": 2297,
    "rau": 3675,
    "aum": 945,
    "trau": 4373,
    "raum": 3676,
    "auma": 946,
    "uma ": 4547,
    "cel": 1142,
    "los": 2679,
    " cel": 103,
    "celo": 1145,
    "elos": 1620,
    "los ": 2680,
    "nfu": 3003,
    "fus": 1975,
    "onfu": 3331,
    "nfus": 3004,
    "fusi": 1976,
    "usió": 4605,
    "azo": 974,
    "hazo": 2095,
    "azo ": 975,
    "ral": 3656,
    "iza": 2464,
    "zan": 4797,
    "aral": 859,
    "rali": 3657,
    "aliz": 745,
    "liza": 2641,
    "izan": 2467,
    "zant": 4798,
    "umi": 4554,
    "lad": 2534,
    "humi": 2139,
    "umil": 4556,
    "illa": 2280,
    "llad": 2644,
    "lado": 2536,
    "rie": 3789,
    "erie": 1756,
    "rien": 3790,
    "ienc": 2229,
    "sad": 3976,
    "asad": 899,
    "sada": 3977,
    "adas": 669,
    "uf": 4505,
    "suf": 4203,
    "ufr": 4506,
    "fro": 1958,
    " suf": 525,
    "sufr": 4204,
    "ufro": 4507,
    "fro ": 1959,
    "oi": 3248,
    "noi": 3052,
    "oia": 3249,
    "aran": 861,
    "rano": 3667,
    "anoi": 816,
    "noia": 3053,
    "oia ": 3250,
    "pc": 3488,
    "cep": 1150,
    "epc": 1714,
    "pci": 3489,
    "dece": 1366,
    "ecep": 1522,
    "cepc": 1151,
    "epci": 1715,
    "pció": 3490,
    "osp": 3419,
    "spr": 4150,
    "iad": 2149,
    "meno": 2805,
    "nosp": 3060,
    "ospr": 3420,
    "spre": 4151,
    "ciad": 1183,
    "iado": 2150,
    " ren": 479,
    "renc": 3737,
    "ncor": 2951,
    "cor ": 1254,
    " li": 331,
    "lib": 2620,
    "ibe": 2172,
    " lib": 332,
    "libe": 2621,
    "iber": 2173,
    "bera": 1020,
    "rarm": 3671,
    " fo": 233,
    "fob": 1946,
    "obi": 3186,
    " fob": 234,
    "fobi": 1947,
    "obia": 3187,
    "iza ": 2465,
    "tad": 4230,
    "ecta": 1543,
    "ctad": 1284,
    "tado": 4233,
    "opi": 3357,
    "pia": 3520,
    "ropi": 3862,
    "opia": 3358,
    "pias": 3521,
    "pot": 3566,
    "ote": 3431,
    "impo": 2304,
    "mpot": 2877,
    "pote": 3567,
    "oten": 3432,
    "espr": 1829,
    "oq": 3366,
    " bl": 78,
    "blo": 1055,
    "loq": 2673,
    "oqu": 3367,
    "ueo": 4490,
    "eo ": 1702,
    " blo": 79,
    "bloq": 1057,
    "loqu": 2674,
    "oque": 3368,
    "queo": 3623,
    "ueo ": 4491,
    "esa": 1790,
    "san": 3987,
    "estr": 1838,
    "stre": 4186,
    "tres": 4378,
    "resa": 3751,
    "esan": 1794,
    "sant": 3988,
    "undo": 4571,
    " ina": 297,
    "inad": 2311,
    "nade": 2916,
    "decu": 1368,
    "ecua": 1548,
    "cuac": 1296,
    "cen": 1148,
    "conc": 1245,
    "ncen": 2938,
    "cent": 1149,
    "trar": 4371,
    "olo": 3272,
    "solo": 4123,
    "olo ": 3273,
    "cos": 1258,
    "osa": 3409,
    "sas": 3995,
    " cos": 118,
    "cosa": 1260,
    "osas": 3412,
    "sas ": 3996,
    "neg": 2978,
    "ega": 1574,
    "gat": 1998,
    "ati": 936,
    "iva": 2449,
    " neg": 389,
    "nega": 2979,
    "egat": 1576,
    "gati": 1999,
    "ativ": 938,
    "tiva": 4335,
    "ivas": 2452,
    "pada": 3463,
    "icu": 2197,
    "ult": 4543,
    "lta": 2696,
    "difi": 1428,
    "ficu": 1930,
    "icul": 2198,
    "cult": 1312,
    "ulta": 4544,
    "ltad": 2698,
    "tad ": 4231,
    "tom": 4349,
    "oma": 3285,
    " tom": 550,
    "toma": 4350,
    "omar": 3287,
    "mar ": 2767,
    "isi": 2407,
    "cisi": 1215,
    "isio": 2408,
    "sion": 4086,
    "rl": 3812,
    " da": 135,
    "arl": 879,
    "rle": 3813,
    " dar": 137,
    "darl": 1349,
    "arle": 880,
    "rle ": 3814,
    "vue": 4735,
    "elt": 1621,
    " vue": 589,
    "vuel": 4736,
    "uelt": 4483,
    "elta": 1622,
    "ltas": 2699,
    "lv": 2720,
    " ol": 417,
    "olv": 3279,
    "lvi": 2723,
    "vid": 4703,
    " olv": 418,
    "olvi": 3281,
    "lvid": 2724,
    "vido": 4706,
    "fá": 1979,
    "ác": 4823,
    " fá": 245,
    "fác": 1980,
    "áci": 4824,
    "ilm": 2282,
    " fác": 246,
    "fáci": 1981,
    "ácil": 4825,
    "cilm": 1201,
    "ilme": 2283,
    "mem": 2802,
    "ori": 3387,
    "ria": 3777,
    " mem": 360,
    "memo": 2803,
    "emor": 1640,
    "mori": 2855,
    "oria": 3388,
    "ria ": 3778,
    "fal": 1901,
    "all": 746,
    " fal": 222,
    "fall": 1902,
    "alla": 747,
    "land": 2544,
    "cues": 1306,
    "mant": 2764,
    "tene": 4275,
    "ener": 1668,
    "ner ": 2985,
    "sam": 3985,
    "pens": 3501,
    "nsam": 3078,
    "sami": 3986,
    "amie": 781,
    "tru": 4386,
    "siv": 4096,
    "vos": 4730,
    "intr": 2344,
    "ntru": 3133,
    "trus": 4389,
    "rusi": 3930,
    "usiv": 4604,
    "sivo": 4098,
    "ivos": 2461,
    "vos ": 4731,
    "ani": 811,
    "nif": 3025,
    "plan": 3539,
    "lani": 2546,
    "anif": 812,
    "nifi": 3026,
    "fica": 1927,
    "car ": 1119,
    "ago": 694,
    "gob": 2019,
    "iar": 2161,
    " ago": 20,
    "agob": 695,
    "gobi": 2020,
    "biar": 1029,
    "iarm": 2165,
    "rai": 3654,
    "aig": 707,
    "dist": 1447,
    "istr": 2427,
    "trai": 4369,
    "raig": 3655,
    "aigo": 708,
    "lq": 2686,
    "alq": 756,
    "lqu": 2687,
    "uie": 4516,
    "cual": 1298,
    "ualq": 4434,
    "alqu": 757,
    "lqui": 2688,
    "quie": 3628,
    "uier": 4517,
    "ier ": 2237,
    "osa ": 3410,
    "nub": 3141,
    "ubl": 4440,
    " nub": 402,
    "nubl": 3142,
    "ubla": 4441,
    "blad": 1048,
    "lada": 2535,
    "osi": 3413,
    "sib": 4063,
    "posi": 3565,
    "osib": 3414,
    "sibl": 4065,
    "ari": 875,
    "lari": 2555,
    "arid": 877,
    "eos": 1709,
    "ueos": 4492,
    "eos ": 1710,
    "ntal": 3106,
    "tale": 4236,
    " or": 424,
    "org": 3385,
    "rga": 3768,
    "gan": 1990,
    "niz": 3037,
    "zar": 4799,
    " org": 426,
    "orga": 3386,
    "rgan": 3769,
    "gani": 1993,
    "aniz": 813,
    "niza": 3038,
    "izar": 2468,
    "zar ": 4800,
    " id": 291,
    "ide": 2207,
    "dea": 1361,
    " ide": 292,
    "idea": 2208,
    "deas": 1362,
    "blar": 1050,
    "fl": 1940,
    " fl": 230,
    "flu": 1943,
    "lui": 2715,
    "uid": 4512,
    " flu": 232,
    "flui": 1944,
    "luid": 2716,
    "uide": 4514,
    "idez": 2212,
    "dez ": 1408,
    "eco": 1538,
    "reco": 3718,
    "ecor": 1540,
    "orda": 3380,
    "rdar": 3691,
    "rsac": 3892,
    "ecie": 1533,
    "cien": 1196,
    "rend": 3738,
    "der ": 1391,
    "xt": 4766,
    "tex": 4290,
    "ext": 1880,
    "xto": 4767,
    " tex": 543,
    "text": 4291,
    "exto": 1881,
    "xtos": 4768,
    "mpl": 2871,
    "ple": 3540,
    "lej": 2592,
    "jos": 2508,
    "ompl": 3305,
    "mple": 2872,
    "plej": 3541,
    "lejo": 2593,
    "ejos": 1598,
    "jos ": 2509,
    "bs": 1080,
    " ob": 411,
    "obs": 3194,
    "bse": 1081,
    " obs": 412,
    "obse": 3195,
    "bses": 1082,
    "esio": 1813,
    "iono": 2360,
    "ono ": 3338,
    "det": 1405,
    "eta": 1843,
    " det": 150,
    "deta": 1406,
    "etal": 1845,
    "tall": 4238,
    "alle": 748,
    "lles": 2650,
    "rel": 3729,
    "ele": 1608,
    "lev": 2607,
    "eva": 1855,
    "van": 4670,
    "irre": 2391,
    "rrel": 3882,
    "rele": 3731,
    "elev": 1611,
    "leva": 2608,
    "evan": 1856,
    "vant": 4671,
    "rio": 3798,
    "ior": 2361,
    "riz": 3810,
    "prio": 3583,
    "rior": 3799,
    "iori": 2362,
    "oriz": 3391,
    "riza": 3811,
    "cur": 1315,
    "urr": 4591,
    "ecur": 1550,
    "curr": 1316,
    "urre": 4592,
    "rren": 3883,
    "log": 2668,
    "gro": 2033,
    " log": 341,
    "logr": 2670,
    "ogro": 3242,
    "gro ": 2034,
    "lve": 2721,
    "reso": 3756,
    "esol": 1822,
    "solv": 4125,
    "olve": 3280,
    "lver": 2722,
    "ver ": 4693,
    "obl": 3188,
    "lem": 2594,
    "prob": 3586,
    "robl": 3842,
    "oble": 3189,
    "blem": 1053,
    "lema": 2595,
    "emas": 1631,
    " sim": 513,
    "simp": 4082,
    "impl": 2303,
    "ples": 3542,
    "aut": 953,
    "uto": 4624,
    "toc": 4342,
    "ocr": 3211,
    "iti": 2440,
    " aut": 63,
    "auto": 954,
    "utoc": 4627,
    "tocr": 4343,
    "ocri": 3213,
    "crit": 1277,
    "riti": 3808,
    "itic": 2441,
    "tico": 4301,
    "xc": 4746,
    "exc": 1870,
    "xce": 4747,
    "vam": 4668,
    " exc": 212,
    "exce": 1871,
    "xces": 4748,
    "esiv": 1816,
    "siva": 4097,
    "ivam": 2451,
    "vame": 4669,
    "ueva": 4503,
    "evas": 1857,
    "rete": 3759,
    "eten": 1848,
    "omo": 3301,
    "como": 1241,
    "omo ": 3302,
    "xpr": 4764,
    "expr": 1879,
    "xpre": 4765,
    "esar": 1796,
    "oh": 3243,
    "coh": 1231,
    "ohe": 3244,
    " coh": 113,
    "cohe": 1232,
    "oher": 3245,
    "here": 2104,
    "cap": 1116,
    "pac": 3460,
    " cap": 98,
    "capa": 1117,
    "apac": 836,
    "paci": 3461,
    "acid": 645,
    "cida": 1192,
    "zon": 4812,
    "razo": 3680,
    "azon": 976,
    "zona": 4813,
    "onam": 3317,
    "nami": 2926,
    "ha ": 2062,
    " ha ": 263,
    "smi": 4109,
    "inu": 2345,
    "nui": 3147,
    "dism": 1444,
    "ismi": 2415,
    "smin": 4110,
    "minu": 2829,
    "inui": 2347,
    "nuid": 3148,
    "uido": 4515,
    "ju": 2510,
    "uz": 4638,
    "zg": 4804,
    " ju": 316,
    "juz": 2515,
    "uzg": 4639,
    "zgo": 4805,
    " juz": 318,
    "juzg": 2516,
    "uzgo": 4640,
    "zgo ": 4806,
    "óf": 4920,
    "cat": 1129,
    "tró": 4392,
    "róf": 3960,
    "ófi": 4921,
    " cat": 100,
    "cata": 1130,
    "atas": 930,
    "tast": 4259,
    "astr": 923,
    "stró": 4189,
    "tróf": 4393,
    "rófi": 3961,
    "ófic": 4922,
    "fico": 1929,
    "icos": 2196,
    "cos ": 1259,
    "anti": 825,
    "ntic": 3119,
    "tici": 4300,
    "icip": 2192,
    "cipo": 1211,
    " he ": 272,
    "did": 1419,
    "perd": 3507,
    "erdi": 1745,
    "rdid": 3699,
    "dido": 1421,
    "eat": 1507,
    "ivi": 2455,
    "reat": 3711,
    "eati": 1508,
    "tivi": 4336,
    "ivid": 2456,
    "vida": 4704,
    "nn": 3044,
    "ov": 3439,
    "inn": 2334,
    "nno": 3045,
    "nov": 3064,
    "ova": 3440,
    " inn": 302,
    "inno": 2335,
    "nnov": 3046,
    "nova": 3065,
    "ovac": 3441,
    "vaci": 4662,
    "vis": 4713,
    "isu": 2428,
    "sua": 4199,
    " vis": 583,
    "visu": 4716,
    "isua": 2429,
    "sual": 4200,
    "uali": 4433,
    "olu": 3276,
    "luc": 2705,
    "uci": 4452,
    "solu": 4124,
    "oluc": 3277,
    "luci": 2708,
    "ucio": 4454,
    "lc": 2568,
    "cal": 1102,
    "alc": 727,
    "lcu": 2573,
    "ula": 4534,
    " cal": 95,
    "calc": 1105,
    "alcu": 730,
    "lcul": 2574,
    "cula": 1310,
    "ular": 4536,
    " o ": 410,
    "nú": 3173,
    "úm": 4950,
    " nú": 407,
    "núm": 3176,
    "úme": 4951,
    "mer": 2809,
    "ero": 1765,
    "ros": 3865,
    " núm": 408,
    "núme": 3177,
    "úmer": 4952,
    "mero": 2811,
    "eros": 1767,
    "ros ": 3866,
    "talm": 4239,
    "len": 2597,
    " len": 329,
    "lent": 2598,
    "fina": 1936,
    "inal": 2312,
    "nali": 2922,
    "ps": 3597,
    "lap": 2548,
    "aps": 847,
    "psu": 3602,
    "sus": 4213,
    " lap": 322,
    "laps": 2549,
    "apsu": 848,
    "psus": 3603,
    "sus ": 4214,
    " ri": 484,
    "rig": 3791,
    "igi": 2260,
    "gid": 2011,
    " rig": 485,
    "rigi": 3792,
    "igid": 2261,
    "gide": 2012,
    "mag": 2752,
    "agi": 692,
    "gin": 2015,
    "nar": 2927,
    " ima": 294,
    "imag": 2288,
    "magi": 2753,
    "agin": 693,
    "gina": 2016,
    "inar": 2313,
    "nar ": 2928,
    " pos": 450,
    "osit": 3416,
    "siti": 4093,
    "itiv": 2442,
    "abo": 627,
    "teo": 4280,
    "utos": 4630,
    "tosa": 4358,
    "osab": 3411,
    "sabo": 3973,
    "abot": 629,
    "bote": 1070,
    "oteo": 3433,
    "teo ": 4281,
    "iá": 2469,
    "diá": 1450,
    "iál": 2470,
    "álo": 4828,
    "ogo": 3237,
    " diá": 161,
    "diál": 1451,
    "iálo": 2471,
    "álog": 4829,
    "logo": 2669,
    "ogo ": 3238,
    "rno": 3837,
    "nter": 3116,
    "erno": 1764,
    "rno ": 3838,
    "ít": 4894,
    "crí": 1278,
    "rít": 3957,
    "íti": 4895,
    " crí": 123,
    "crít": 1279,
    "ríti": 3958,
    "ític": 4896,
    "oz": 3450,
    "noz": 3066,
    "ozc": 3451,
    "econ": 1539,
    "onoz": 3340,
    "nozc": 3067,
    "ozco": 3452,
    "got": 2023,
    "ota": 3425,
    "agot": 696,
    "gota": 2024,
    "otad": 3427,
    "lec": 2582,
    "ctu": 1292,
    "ura": 4584,
    " lec": 327,
    "lect": 2583,
    "ectu": 1546,
    "ctur": 1293,
    "tura": 4402,
    "uras": 4585,
    "tade": 4232,
    "ades": 675,
    "uir": 4522,
    "guir": 2045,
    "uir ": 4523,
    "cc": 1133,
    "ruc": 3921,
    "ucc": 4445,
    "cci": 1136,
    "inst": 2341,
    "nstr": 3098,
    "stru": 4187,
    "truc": 4388,
    "rucc": 3922,
    "ucci": 4446,
    "ccio": 1137,
    "senc": 4032,
    "ncil": 2944,
    "cill": 1200,
    "llas": 2647,
    " ord": 425,
    "orde": 3381,
    "rden": 3694,
    "dena": 1383,
    "enar": 1654,
    "orid": 3389,
    "dade": 1340,
    "rsi": 3896,
    "igu": 2266,
    "gue": 2040,
    "ersi": 1777,
    "rsig": 3897,
    "sigu": 4079,
    "igue": 2267,
    "guen": 2041,
    "sec": 4021,
    "esec": 1805,
    "sech": 4023,
    "har ": 2079,
    "sor": 4133,
    "tac": 4227,
    "deso": 1402,
    "esor": 1823,
    "sori": 4134,
    "orie": 3390,
    "ntac": 3104,
    "taci": 4228,
    "iac": 2147,
    "diso": 1445,
    "isoc": 2419,
    "ciac": 1182,
    "iaci": 2148,
    "rrea": 3879,
    "eali": 1499,
    "stu": 4190,
    "tud": 4399,
    "estu": 1839,
    "stud": 4191,
    "tudi": 4400,
    "udia": 4465,
    "diar": 1413,
    "iar ": 2162,
    "dor": 1463,
    "mir": 2831,
    " dor": 165,
    "dorm": 1466,
    "ormi": 3395,
    "rmir": 3829,
    "mir ": 2832,
    " can": 97,
    "nsad": 3076,
    "sado": 3978,
    "dol": 1456,
    " dol": 163,
    "dolo": 1457,
    "olor": 3275,
    "lore": 2677,
    "cab": 1096,
    "bez": 1024,
    " cab": 94,
    "cabe": 1097,
    "abez": 619,
    "beza": 1025,
    "mé": 2899,
    "éd": 4855,
    " mé": 380,
    "méd": 2900,
    "édi": 4856,
    "ca ": 1095,
    " méd": 381,
    "médi": 2901,
    "édic": 4857,
    "dica": 1416,
    "ica ": 2182,
    "ape": 841,
    "pet": 3515,
    "tit": 4332,
    " ape": 45,
    "apet": 842,
    "peti": 3516,
    "etit": 1853,
    "tito": 4333,
    "dig": 1429,
    "ges": 2005,
    " dig": 156,
    "dige": 1430,
    "iges": 2259,
    "gest": 2006,
    "stiv": 4178,
    "ré": 3947,
    "tré": 4390,
    "rés": 3948,
    "stré": 4188,
    "trés": 4391,
    "rés ": 3949,
    "tens": 4278,
    "mus": 2888,
    "usc": 4597,
    " mus": 375,
    "musc": 2889,
    "uscu": 4599,
    "scul": 4012,
    "mn": 2840,
    "som": 4126,
    "omn": 3299,
    "mni": 2841,
    "nio": 3029,
    "inso": 2340,
    "nsom": 3094,
    "somn": 4127,
    "omni": 3300,
    "mnio": 2842,
    "nio ": 3030,
    "cró": 1280,
    "rón": 3962,
    "óni": 4932,
    " cró": 124,
    "crón": 1281,
    "róni": 3963,
    "ónic": 4933,
    "alp": 754,
    "lpi": 2684,
    "pit": 3534,
    "palp": 3470,
    "alpi": 755,
    "lpit": 2685,
    "pita": 3535,
    "itac": 2434,
    "je": 2494,
    "rc": 3684,
    " ej": 180,
    "eje": 1593,
    "jer": 2495,
    "erc": 1740,
    "rci": 3685,
    "cic": 1189,
    " eje": 181,
    "ejer": 1594,
    "jerc": 2496,
    "erci": 1741,
    "rcic": 3686,
    "cici": 1190,
    "icio": 2191,
    "emb": 1632,
    "mbl": 2787,
    " tem": 540,
    "temb": 4270,
    "embl": 1633,
    "mblo": 2789,
    "blor": 1058,
    "anos": 817,
    " ga": 250,
    " gan": 251,
    "gana": 1991,
    "anad": 794,
    "peso": 3514,
    "iet": 2244,
    " die": 154,
    "diet": 1425,
    "ieta": 2245,
    "eta ": 1844,
    "rlo": 3815,
    "tarl": 4254,
    "arlo": 881,
    "rlo ": 3816,
    "sud": 4201,
    " sud": 524,
    "sudo": 4202,
    "udor": 4470,
    "dora": 1465,
    "orac": 3373,
    "rep": 3745,
    "epe": 1716,
    "tin": 4320,
    " rep": 480,
    "repe": 3747,
    "epen": 1717,
    "pent": 3502,
    "ntin": 3123,
    "tina": 4321,
    "inas": 2314,
    " mar": 352,
    "mare": 2768,
    "areo": 870,
    "reos": 3744,
    "fat": 1909,
    "iga": 2255,
    "ga ": 1987,
    " fat": 224,
    "fati": 1910,
    "atig": 937,
    "tiga": 4311,
    "iga ": 2256,
    "nica": 3018,
    "lor ": 2676,
    "ld": 2575,
    "spa": 4138,
    "ald": 731,
    "lda": 2576,
    "espa": 1825,
    "spal": 4139,
    "pald": 3468,
    "alda": 732,
    "lda ": 2577,
    " op": 421,
    "opr": 3362,
    " opr": 423,
    "opre": 3363,
    "resi": 3755,
    " pec": 437,
    "pech": 3493,
    "uic": 4509,
    " taq": 535,
    "aqui": 852,
    "quic": 3627,
    "uica": 4510,
    "card": 1120,
    "ardi": 864,
    "dias": 1414,
    "iel": 2223,
    "piel": 3525,
    "iel ": 2224,
    " ec": 176,
    "ecc": 1517,
    "cce": 1134,
    "cem": 1146,
    " ecc": 177,
    "ecce": 1518,
    "ccem": 1135,
    "cema": 1147,
    " ps": 456,
    "pso": 3600,
    " pso": 458,
    "psor": 3601,
    "rias": 3782,
    "iasi": 2169,
    "sis ": 4089,
    "eq": 1726,
    "seq": 4038,
    "equ": 1727,
    " seq": 505,
    "sequ": 4039,
    "eque": 1728,
    "qued": 3622,
    "ueda": 4475,
    "boc": 1061,
    "oca": 3197,
    " boc": 81,
    "boca": 1062,
    "oca ": 3198,
    "pir": 3530,
    "ira": 2378,
    "spir": 4147,
    "pira": 3531,
    "irar": 2380,
    "aho": 701,
    "hog": 2123,
    " aho": 23,
    "ahog": 702,
    "hogo": 2125,
    "ná": 3165,
    "áu": 4850,
    " ná": 405,
    "náu": 3166,
    "áus": 4851,
    "use": 4600,
    "sea": 4019,
    " náu": 406,
    "náus": 3167,
    "áuse": 4852,
    "usea": 4601,
    "seas": 4020,
    "vó": 4739,
    " vó": 591,
    "vóm": 4740,
    "ómi": 4924,
    "mit": 2837,
    " vóm": 592,
    "vómi": 4741,
    "ómit": 4925,
    "mito": 2839,
    "itos": 2445,
    " dia": 152,
    "iarr": 2166,
    "rv": 3937,
    "erv": 1782,
    "rvi": 3940,
    "vio": 4709,
    " ner": 390,
    "nerv": 2987,
    "ervi": 1784,
    "rvio": 3941,
    "vios": 4710,
    "ñi": 4908,
    "reñ": 3765,
    "eñi": 1893,
    "ñim": 4909,
    "treñ": 4379,
    "reñi": 3766,
    "eñim": 1894,
    "ñimi": 4910,
    "rtic": 3912,
    "ticu": 4302,
    "ulac": 4535,
    "laci": 2533,
    "cac": 1098,
    "icac": 2183,
    "caci": 1099,
    "mec": 2794,
    " ado": 16,
    "ador": 682,
    "orme": 3394,
    "rmec": 3824,
    "meci": 2795,
    "ecim": 1534,
    "xtr": 4769,
    "rem": 3732,
    "emi": 1636,
    " ext": 216,
    "extr": 1882,
    "xtre": 4771,
    "trem": 4376,
    "remi": 3734,
    "emid": 1637,
    "mida": 2815,
    "visi": 4714,
    "isió": 2410,
    "bor": 1065,
    "orr": 3402,
    " bor": 83,
    "borr": 1067,
    "orro": 3404,
    "rros": 3889,
    "rosa": 3867,
    "esad": 1792,
    " z": 597,
    "zu": 4815,
    " zu": 598,
    "zum": 4816,
    "umb": 4550,
    "bid": 1030,
    " zum": 599,
    "zumb": 4817,
    "umbi": 4551,
    "mbid": 2785,
    "bido": 1031,
    "idos": 2215,
    " los": 342,
    "oí": 3453,
    " oí": 429,
    "oíd": 3454,
    "ído": 4879,
    " oíd": 430,
    "oído": 3455,
    "ídos": 4880,
    "chi": 1175,
    "hin": 2115,
    "echi": 1527,
    "chin": 1176,
    "hina": 2116,
    "ux": 4633,
    " br": 85,
    "rux": 3935,
    "uxi": 4634,
    "xis": 4756,
    " bru": 86,
    "brux": 1079,
    "ruxi": 3936,
    "uxis": 4635,
    "xism": 4757,
    "hip": 2117,
    "ipe": 2371,
    "rse": 3894,
    " hip": 279,
    "hipe": 2118,
    "iper": 2372,
    "erse": 1776,
    "rsen": 3895,
    "nsib": 3086,
    "sibi": 4064,
    "ibil": 2176,
    " ru": 490,
    "rui": 3923,
    " rui": 491,
    "ruid": 3924,
    "uce": 4447,
    " luc": 344,
    "luce": 2706,
    "uces": 4448,
    "eca": 1515,
    " sec": 501,
    "seca": 4022,
    "eca ": 1516,
    "rag": 3652,
    "aga": 690,
    "gar": 1994,
    "trag": 4368,
    "raga": 3653,
    "agar": 691,
    "gar ": 1995,
    "cala": 1104,
    "alam": 726,
    "lamb": 2539,
    "ambr": 776,
    "bres": 1076,
    "lare": 2553,
    "ares": 871,
    "saj": 3979,
    "aju": 720,
    "jus": 2513,
    "desa": 1397,
    "esaj": 1793,
    "saju": 3981,
    "ajus": 721,
    "just": 2514,
    "uste": 4610,
    "stes": 4171,
    "hor": 2130,
    "rmo": 3830,
    "mon": 2851,
    " hor": 283,
    "horm": 2132,
    "ormo": 3396,
    "rmon": 3832,
    "mona": 2852,
    "rua": 3919,
    "mens": 2806,
    "enst": 1686,
    "trua": 4387,
    "rual": 3920,
    "uale": 4432,
    " rel": 478,
    "rela": 3730,
    "elac": 1604,
    "onad": 3315,
    "ados": 683,
    "aí": 979,
    "caí": 1131,
    "aíd": 980,
    " caí": 101,
    "caíd": 1132,
    "aída": 981,
    "ída ": 4877,
    "bel": 1016,
    "ell": 1616,
    "llo": 2651,
    "abel": 617,
    "bell": 1017,
    "ello": 1617,
    "llo ": 2652,
    "iva ": 2450,
    "ler": 2599,
    "rgi": 3770,
    "aler": 735,
    "lerg": 2601,
    "ergi": 1751,
    "rgia": 3771,
    "gias": 2010,
    "mpe": 2866,
    "peo": 3503,
    "eor": 1707,
    " emp": 187,
    "empe": 1644,
    "mpeo": 2867,
    "peor": 3504,
    "eora": 1708,
    "oran": 3375,
    "ran ": 3664,
    "rve": 3938,
    "ila": 2273,
    "perv": 3510,
    "erve": 1783,
    "rven": 3939,
    "vent": 4689,
    "ntil": 3121,
    "tila": 4315,
    "ilac": 2274,
    "rter": 3910,
    "teri": 4284,
    "eria": 1754,
    "rial": 3780,
    "alt": 760,
    " alt": 33,
    "alta": 761,
    "lta ": 2697,
    "otam": 3429,
    "tami": 4242,
    "fí": 1982,
    "ís": 4891,
    " fí": 247,
    "fís": 1983,
    "ísi": 4892,
    "sic": 4066,
    " fís": 248,
    "físi": 1984,
    "ísic": 4893,
    "sico": 4067,
    "rmig": 3827,
    "migu": 2822,
    "gueo": 2042,
    "rp": 3870,
    "erp": 1768,
    "rpo": 3871,
    "cuer": 1305,
    "uerp": 4498,
    "erpo": 1769,
    "rpo ": 3872,
    "rema": 3733,
    " aci": 9,
    "cide": 1193,
    "aca": 636,
    "stom": 4181,
    "omac": 3286,
    "maca": 2747,
    "acal": 637,
    "cal ": 1103,
    " oj": 415,
    " ojo": 416,
    "ojos": 3256,
    "seco": 4024,
    "ecos": 1541,
    "itad": 2435,
    "onq": 3341,
    " ron": 489,
    "ronq": 3859,
    "onqu": 3342,
    "uera": 4494,
    "era ": 1733,
    "esf": 1809,
    "fri": 1956,
    "resf": 3754,
    "esfr": 1810,
    "sfri": 4053,
    "fria": 1957,
    "riad": 3779,
    "ract": 3647,
    "actu": 659,
    "rsis": 3898,
    "nfe": 2993,
    "fec": 1914,
    "infe": 2323,
    "nfec": 2994,
    "fecc": 1915,
    "ecci": 1519,
    "aja": 714,
    "jad": 2483,
    " baj": 71,
    "baja": 1001,
    "ajad": 715,
    "jada": 2484,
    " def": 143,
    "nsas": 3080,
    "not": 3062,
    " not": 400,
    "nota": 3063,
    "libi": 2622,
    "ibid": 2175,
    "iero": 2238,
    "ero ": 1766,
    "ie ": 2217,
    "nadi": 2917,
    "adie": 678,
    "die ": 1423,
    "jan": 2488,
    "ejan": 1590,
    "jand": 2489,
    "oda": 3217,
    "toda": 4345,
    "odas": 3219,
    "pez": 3517,
    "mpez": 2868,
    "peza": 3518,
    "ezad": 1889,
    " be": 73,
    "beb": 1014,
    " beb": 74,
    "bebe": 1015,
    "ber ": 1019,
    "lco": 2571,
    "oho": 3246,
    " alc": 29,
    "alco": 729,
    "lcoh": 2572,
    "coho": 1233,
    "ohol": 3247,
    "hol ": 2127,
    "ban": 1003,
    "don": 1461,
    " aba": 4,
    "aban": 615,
    "band": 1005,
    "ndon": 2968,
    "dona": 1462,
    "cti": 1287,
    " act": 11,
    "acti": 657,
    "ctiv": 1288,
    "utab": 4619,
    "vito": 4719,
    "lir": 2634,
    "sali": 3983,
    "alir": 744,
    "lir ": 2635,
    "cas": 1125,
    " cas": 99,
    "casa": 1127,
    "nsu": 3099,
    "sum": 4207,
    "onsu": 3348,
    "nsum": 3100,
    "sumi": 4208,
    "umie": 4555,
    "iend": 2230,
    "endo": 1665,
    " sus": 528,
    "sust": 4216,
    "usta": 4609,
    "tanc": 4245,
    "anci": 798,
    "lto": 2702,
    "elto": 1623,
    "lto ": 2703,
    "tabl": 4226,
    "sere": 4042,
    "sl": 4101,
    "lá": 2725,
    " ai": 25,
    "ais": 709,
    "isl": 2411,
    "slá": 4104,
    "lán": 2726,
    "ánd": 4831,
    "ome": 3290,
    " ais": 26,
    "aisl": 710,
    "islá": 2413,
    "slán": 4105,
    "lánd": 2727,
    "ándo": 4832,
    "ndom": 2967,
    "dome": 1459,
    "ome ": 3291,
    "ialm": 2155,
    "cui": 1307,
    "scui": 4011,
    "cuid": 1308,
    "uida": 4513,
    "dado": 1341,
    "hig": 2113,
    "gie": 2013,
    "ne ": 2973,
    " hig": 278,
    "higi": 2114,
    "igie": 2262,
    "gien": 2014,
    "ene ": 1667,
    "roc": 3844,
    "ino": 2336,
    "proc": 3587,
    "rocr": 3846,
    "ocra": 3212,
    "cras": 1268,
    "rast": 3674,
    "asti": 921,
    "stin": 4177,
    "tino": 4323,
    "ino ": 2337,
    "ume": 4552,
    " aum": 61,
    "aume": 947,
    "umen": 4553,
    "ntad": 3105,
    "sumo": 4209,
    "umo ": 4558,
    "omid": 3295,
    "ida ": 2201,
    "ls": 2689,
    "mpu": 2881,
    "pul": 3608,
    "uls": 4541,
    "lsi": 2690,
    "ompu": 3308,
    "mpul": 2882,
    "puls": 3609,
    "ulsi": 4542,
    "lsiv": 2692,
    "fum": 1970,
    " fum": 242,
    "fuma": 1971,
    "uman": 4549,
    "mand": 2760,
    " llo": 337,
    "llor": 2653,
    "uenc": 4487,
    "pod": 3550,
    "ode": 3220,
    " pod": 448,
    "pode": 3551,
    "oder": 3221,
    "larl": 2556,
    "sq": 4156,
    "esq": 1831,
    "squ": 4157,
    "uit": 4526,
    "desq": 1404,
    "esqu": 1832,
    "squi": 4158,
    "quit": 3630,
    "uito": 4528,
    "tros": 4385,
    "nj": 3041,
    "inj": 2332,
    "nju": 3042,
    " inj": 301,
    "inju": 2333,
    "njus": 3043,
    "stam": 4164,
    "uti": 4622,
    " rut": 492,
    "ruti": 3934,
    "utin": 4623,
    "iari": 2164,
    "aria": 876,
    "amad": 770,
    "mada": 2750,
    "aje": 716,
    "jes": 2497,
    "nsaj": 3077,
    "saje": 3980,
    "ajes": 717,
    "jes ": 2498,
    "idan": 2204,
    "pons": 3558,
    "onsa": 3344,
    "nsab": 3074,
    "sabi": 3972,
    "slo": 4102,
    "islo": 2412,
    "slo ": 4103,
    "fam": 1905,
    "lia": 2617,
    " fam": 223,
    "fami": 1906,
    "amil": 783,
    "mili": 2825,
    "ilia": 2277,
    "lia ": 2618,
    "gos": 2021,
    "igos": 2265,
    "gos ": 2022,
    "ejad": 1589,
    "jado": 2485,
    "med": 2796,
    "edi": 1558,
    " med": 357,
    "medi": 2797,
    "edic": 1559,
    "rip": 3801,
    "ipc": 2369,
    "resc": 3752,
    "crip": 1275,
    "ripc": 3802,
    "ipci": 2370,
    "duer": 1481,
    "uerm": 4497,
    "ermo": 1761,
    "rmo ": 3831,
    "dem": 1379,
    " dem": 146,
    "dema": 1380,
    "masi": 2775,
    "asia": 910,
    "siad": 4061,
    "enf": 1670,
    "nfr": 3001,
    " enf": 191,
    "enfr": 1671,
    "nfre": 3002,
    "fren": 1955,
    "udio": 4466,
    "ndu": 2969,
    "duc": 1475,
    "uct": 4455,
    "cond": 1246,
    "ondu": 3325,
    "nduc": 2970,
    "duct": 1476,
    "ucta": 4456,
    "ctas": 1286,
    "gre": 2031,
    "agre": 699,
    "gres": 2032,
    "nus": 3151,
    "usu": 4614,
    " inu": 305,
    "inus": 2348,
    "nusu": 3152,
    "usua": 4615,
    "falt": 1904,
    "alto": 762,
    "scue": 4010,
    "cuel": 1303,
    "uela": 4481,
    "ela ": 1602,
    "come": 1239,
    "omer": 3293,
    "mer ": 2810,
    "reg": 3725,
    "gul": 2046,
    " reg": 477,
    "regu": 3726,
    "egul": 1584,
    "gula": 2047,
    "larm": 2557,
    "rmen": 3825,
    "mpro": 2880,
    "pro ": 3585,
    "jue": 2511,
    " jue": 317,
    "jueg": 2512,
    "deo": 1386,
    "eoj": 1705,
    "oju": 3257,
    " vid": 581,
    "vide": 4705,
    "ideo": 2210,
    "deoj": 1387,
    "eoju": 1706,
    "ojue": 3258,
    "egos": 1579,
    "scap": 4000,
    "par ": 3474,
    "tact": 4229,
    "acto": 658,
    "emá": 1647,
    "demá": 1381,
    "emás": 1648,
    "pari": 3477,
    "arie": 878,
    "rev": 3761,
    " rev": 483,
    "revi": 3762,
    "evis": 1863,
    "viso": 4715,
    "iso ": 2418,
    "lé": 2728,
    "éf": 4858,
    "elé": 1624,
    "léf": 2729,
    "éfo": 4859,
    "fon": 1948,
    " tel": 539,
    "telé": 4267,
    "eléf": 1625,
    "léfo": 2730,
    "éfon": 4860,
    "fono": 1949,
    " red": 475,
    "tol": 4347,
    "utol": 4628,
    "tole": 4348,
    "oles": 3268,
    "lesi": 2604,
    "mal": 2754,
    " mal": 350,
    "mal ": 2755,
    "isc": 2400,
    "cut": 1317,
    "disc": 1441,
    "iscu": 2402,
    "scut": 4013,
    "cuto": 1318,
    "uto ": 4625,
    "liar": 2619,
    "iare": 2163,
    "usp": 4606,
    "susp": 4215,
    "uspe": 4607,
    "spen": 4143,
    "rom": 3855,
    "sos": 4135,
    "prom": 3591,
    "romi": 3856,
    "omis": 3298,
    "miso": 2836,
    "isos": 2421,
    "sos ": 4136,
    "timo": 4319,
    "mom": 2849,
    " mom": 369,
    "mome": 2850,
    "omen": 3292,
    "bb": 1010,
    "hob": 2121,
    "obb": 3184,
    "bbi": 1011,
    "ies": 2241,
    " hob": 281,
    "hobb": 2122,
    "obbi": 3185,
    "bbie": 1012,
    "bies": 1034,
    "ies ": 2242,
    "nab": 2910,
    "apas": 839,
    "pasi": 3482,
    "asio": 912,
    "onab": 3314,
    "naba": 2911,
    "ban ": 1004,
    "ncie": 2943,
    "bit": 1044,
    "habi": 2064,
    "abit": 622,
    "bita": 1045,
    "arg": 873,
    "rgo": 3772,
    " lar": 323,
    "larg": 2554,
    "argo": 874,
    "rgos": 3773,
    "río": 3954,
    "íod": 4889,
    "perí": 3511,
    "erío": 1787,
    "ríod": 3956,
    "íodo": 4890,
    "ham": 2071,
    " ham": 266,
    "hamb": 2072,
    "lon": 2671,
    "ong": 3332,
    "gad": 1988,
    "prol": 3590,
    "rolo": 3854,
    "olon": 3274,
    "long": 2672,
    "onga": 3333,
    "ngad": 3007,
    "gado": 1989,
    " ira": 309,
    "ira ": 2379,
    "opo": 3360,
    "orc": 3377,
    "spro": 4152,
    "ropo": 3863,
    "opor": 3361,
    "porc": 3561,
    "orci": 3378,
    "rcio": 3687,
    "ealm": 1500,
    "asc": 901,
    "cot": 1263,
    " mas": 353,
    "masc": 2774,
    "asco": 902,
    "scot": 4004,
    "cota": 1264,
    "otas": 3430,
    "anta": 823,
    "ceso": 1161,
    "omé": 3309,
    "utom": 4629,
    "tomé": 4351,
    "oméd": 3310,
    "dico": 1418,
    "lma": 2657,
    "calm": 1107,
    "alma": 750,
    "lmar": 2658,
    "marm": 2770,
    "ctos": 1291,
    "pel": 3497,
    "lea": 2580,
    " pel": 438,
    "pele": 3498,
    "elea": 1609,
    "leas": 2581,
    "rej": 3727,
    "arej": 868,
    "reja": 3728,
    "gru": 2035,
    "rup": 3927,
    " gru": 257,
    "grup": 2036,
    "rupa": 3928,
    "upal": 4577,
    "pale": 3469,
    "oda ": 3218,
    "cost": 1262,
    "ort": 3405,
    "rta": 3902,
    "ompo": 3306,
    "mpor": 2875,
    "port": 3562,
    "orta": 3406,
    "rtam": 3905,
    "lim": 2631,
    "mpi": 2869,
    "iez": 2246,
    " lim": 333,
    "limp": 2633,
    "impi": 2302,
    "mpie": 2870,
    "piez": 3527,
    "ieza": 2247,
    "tid": 4303,
    "dam": 1342,
    "epet": 1718,
    "etid": 1851,
    "tida": 4304,
    "idam": 2203,
    "dame": 1343,
    "adu": 684,
    "dur": 1482,
    "rrad": 3876,
    "radu": 3651,
    "adur": 685,
    "dura": 1483,
    " gas": 252,
    "canc": 1112,
    "ance": 797,
    "ncel": 2937,
    "cela": 1143,
    "elad": 1605,
    "lane": 2545,
    "anes": 807,
    "rtan": 3906,
    " ali": 32,
    "alim": 743,
    "lime": 2632,
    "let": 2605,
    "plet": 3543,
    "leta": 2606,
    "etam": 1846,
    "creo": 1271,
    "reo ": 3742,
    "viv": 4720,
    "vie": 4707,
    " viv": 584,
    "vivi": 4721,
    "ivie": 2457,
    "vien": 4708,
    "vec": 4680,
    " vec": 575,
    "vece": 4681,
    "ño": 4911,
    "dañ": 1357,
    "año": 988,
    "ño ": 4912,
    " dañ": 138,
    "daño": 1358,
    "año ": 989,
    "lat": 2565,
    " lat": 325,
    "late": 2566,
    "áp": 4837,
    " rá": 493,
    "ráp": 3943,
    "ápi": 4838,
    " ráp": 494,
    "rápi": 3944,
    "ápid": 4839,
    "esm": 1818,
    "sma": 4107,
    "may": 2778,
    "yar": 4776,
    "desm": 1401,
    "esma": 1819,
    "smay": 4108,
    "maya": 2779,
    "ayar": 964,
    "yar ": 4777,
    "sui": 4205,
    " sui": 526,
    "suic": 4206,
    "uici": 4511,
    "icid": 2190,
    "idas": 2206,
    "sid": 4068,
    "nsid": 3087,
    "side": 4069,
    "ider": 2211,
    "dera": 1392,
    "rand": 3665,
    "uita": 4527,
    "rdie": 3700,
    "last": 2564,
    "imar": 2290,
    "veo": 4690,
    " veo": 577,
    "veo ": 4691,
    "ilan": 2275,
    "sop": 4131,
    "nsop": 3095,
    "sopo": 4132,
    "rtab": 3903,
    "izad": 2466,
    "mbla": 2788,
    "nie": 3022,
    "teni": 4277,
    "enie": 1677,
    "nien": 3024,
    "nfa": 2991,
    "far": 1907,
    "rto": 3914,
    "infa": 2322,
    "nfar": 2992,
    "fart": 1908,
    "arto": 892,
    "rto ": 3915,
    "cian": 1185,
    "iand": 2159,
    "vol": 4726,
    " vol": 586,
    "volv": 4727,
    "verm": 4697,
    "loc": 2666,
    " loc": 340,
    "loco": 2667,
    "cin": 1204,
    "nac": 2912,
    " alu": 34,
    "aluc": 764,
    "ucin": 4453,
    "cina": 1205,
    "inac": 2310,
    "naci": 2913,
    "dó": 1488,
    " dó": 173,
    "dón": 1489,
    "ónd": 4930,
    " dón": 174,
    "dónd": 1490,
    "ónde": 4931,
    "nde ": 2959,
    "mur": 2886,
    " mur": 374,
    "muri": 2887,
    "urie": 4588,
    "mov": 2860,
    "ove": 3442,
    " mov": 371,
    "move": 2861,
    "over": 3443,
    "pap": 3471,
    "empa": 1643,
    "mpap": 2864,
    "papa": 3472,
    "apad": 837,
    "dor ": 1464,
    "frí": 1963,
    " frí": 238,
    "frío": 1964,
    "río ": 3955,
    "ing": 2326,
    "isti": 2426,
    "ting": 4322,
    "ingo": 2327,
    "oa": 3180,
    "toa": 4340,
    "oag": 3181,
    "utoa": 4626,
    "toag": 4341,
    "oagr": 3182,
    " ela": 184,
    "elab": 1603,
    "labo": 2529,
    "abor": 628,
    "bora": 1066,
    "orad": 3374,
    "rado": 3650,
    "lan ": 2542,
    "idar": 2205,
    "rañ": 3682,
    "arí": 893,
    "xtra": 4770,
    "trañ": 4374,
    "raña": 3683,
    "ñarí": 4905,
    "aría": 894,
    "si ": 4059,
    " si ": 510,
    "sap": 3989,
    "rez": 3763,
    "esap": 1795,
    "sapa": 3990,
    "arez": 872,
    "rezc": 3764,
    "seo": 4035,
    "eseo": 1807,
    "seos": 4037,
    "arec": 867,
    "zone": 4814,
    " ade": 14,
    "adel": 673,
    "dela": 1377,
    "ím": 4881,
    " lí": 346,
    "lím": 2734,
    "ími": 4882,
    "ite": 2438,
    " lím": 347,
    "lími": 2735,
    "ímit": 4883,
    "mite": 2838,
    "ite ": 2439,
    "esis": 1814,
    "ntan": 3108,
    "tand": 4246,
    "ñas": 4906,
    "añas": 987,
    "ñas ": 4907,
    " inc": 298,
    "inco": 2317,
    "olab": 3264,
    "labl": 2528,
    "oga": 3235,
    "hoga": 2124,
    "ogan": 3236,
    "gand": 1992,
    " ni": 391,
    "nin": 3027,
    "gun": 2048,
    " nin": 393,
    "ning": 3028,
    "ingu": 2328,
    "ngun": 3012,
    "guna": 2049,
    "aner": 806,
    "tú": 4420,
    "ún": 4953,
    " tú": 558,
    "tún": 4421,
    "úne": 4955,
    "nel": 2982,
    " tún": 559,
    "túne": 4422,
    "únel": 4956,
    "nel ": 2983,
    "lara": 2552,
    "aram": 860,
    "rame": 3660,
    " ace": 8,
    "acel": 640,
    "cele": 1144,
    "eler": 1610,
    "lera": 2600,
    "erad": 1736,
    "lgo": 2613,
    " alg": 31,
    "algo": 739,
    "lgo ": 2614,
    "terr": 4287,
    "erri": 1772,
    "rrib": 3885,
    "ribl": 3785,
    "asar": 900,
    "erde": 1744,
    "rder": 3695,
    "av": 955,
    "rav": 3677,
    "ave": 956,
    "ve ": 4677,
    "grav": 2030,
    "rave": 3678,
    "ave ": 957,
    " sop": 522,
    "rtar": 3907,
    "abs": 633,
    "bso": 1083,
    "lut": 2717,
    " abs": 6,
    "abso": 634,
    "bsol": 1084,
    "olut": 3278,
    "luta": 2718,
    "uta ": 4618,
    "epa": 1712,
    "prep": 3578,
    "repa": 3746,
    "epar": 1713,
    "arad": 858,
    "ota ": 3426,
    "ped": 3495,
    "sped": 4142,
    "pedi": 3496,
    "edid": 1560,
    "dida": 1420,
    " cri": 122,
    "cris": 1276,
    "risi": 3804,
    "isis": 2409,
    "exi": 1874,
    " exi": 214,
    "exis": 1875,
    "xist": 4758,
    "sev": 4047,
    "eve": 1858,
    " sev": 508,
    "seve": 4048,
    "ever": 1860,
    "vera": 4694,
    "luch": 2707,
    "chan": 1165,
    "hand": 2075,
    "stad": 4162,
    " lev": 330,
    "leve": 2609,
    "eve ": 1859,
    "mod": 2847,
    " mod": 368,
    "mode": 2848,
    "vero": 4698,
    "dir": 1438,
    " dir": 159,
    "dirí": 1439,
    "efi": 1570,
    "defi": 1371,
    "efin": 1572,
    "niti": 3033,
    "lif": 2627,
    "cali": 1106,
    "alif": 742,
    "lifi": 2628,
    "carí": 1124,
    "emad": 1629,
    "adam": 668,
    "dero": 1394,
    "ahor": 703,
    "hora": 2131,
    "ora ": 3372,
    "lca": 2569,
    "alca": 728,
    "lcan": 2570,
    "canz": 1115,
    "nzad": 3162,
    "niv": 3035,
    "ive": 2453,
    "vel": 4682,
    " niv": 394,
    "nive": 3036,
    "ivel": 2454,
    "vel ": 4683,
    " ran": 470,
    "rang": 3666,
    "ango": 809,
    "aú": 992,
    " aú": 67,
    "aún": 993,
    "ún ": 4954,
    " aún": 68,
    "aún ": 994,
    "ogre": 3241,
    "lega": 2589,
    "egad": 1575,
    "elat": 1607,
    "lati": 2567,
    "aso": 916,
    "caso": 1128,
    "aso ": 917,
    "dio ": 1436,
    "odr": 3227,
    "drí": 1472,
    "podr": 3552,
    "odrí": 3228,
    "dría": 1473,
    "sif": 4074,
    "lasi": 2563,
    "asif": 911,
    "sifi": 4075,
    "carl": 1121,
    "dud": 1477,
    " dud": 169,
    "duda": 1478,
    "pin": 3528,
    "nió": 3039,
    " opi": 422,
    "opin": 3359,
    "pini": 3529,
    "inió": 2331,
    "nión": 3040,
    "guro": 2052,
    "ece ": 1521,
    "nta ": 3103,
    "fie": 1931,
    "mani": 2762,
    "ifie": 2253,
    "fies": 1933,
    "iest": 2243,
    "evid": 1862,
    "iden": 2209,
    "denc": 1384,
    " dan": 136,
    "dan ": 1345,
    "nden": 2961,
    " ge": 253,
    " gen": 254,
    "gene": 2003,
    "eral": 1737,
    "zada": 4795,
    " son": 521,
    "son ": 4129,
    "epre": 1724,
    "ín": 4884,
    "clí": 1227,
    "lín": 2736,
    "íni": 4885,
    " clí": 111,
    "clín": 1228,
    "líni": 2737,
    "ínic": 4886,
    "sh": 4055,
    "hb": 2096,
    "ks": 2519,
    "fla": 1941,
    "ash": 907,
    "shb": 4056,
    "hba": 2097,
    "bac": 998,
    "cks": 1221,
    "ks ": 2520,
    " fla": 231,
    "flas": 1942,
    "lash": 2562,
    "ashb": 908,
    "shba": 4057,
    "hbac": 2098,
    "back": 999,
    "acks": 651,
    "cks ": 1222,
    "át": 4847,
    "umá": 4560,
    "mát": 2897,
    "áti": 4848,
    "aumá": 948,
    "umát": 4561,
    "máti": 2898,
    "átic": 4849,
    "lsio": 2691,
    "ní": 3168,
    "aní": 830,
    "nía": 3169,
    "íac": 4871,
    "maní": 2765,
    "anía": 831,
    "níac": 3170,
    "íaco": 4872,
    "aco ": 653,
    "psi": 3598,
    " psi": 457,
    "psic": 3599,
    "cosi": 1261,
    "osis": 3415,
    "iri": 2381,
    "deli": 1378,
    "elir": 1614,
    "liri": 2636,
    "irio": 2382,
    "rios": 3800,
    "tor": 4354,
    "tras": 4372,
    "asto": 922,
    "stor": 4182,
    "torn": 4355,
    "orno": 3399,
    "bip": 1039,
    "pol": 3553,
    " bip": 77,
    "bipo": 1040,
    "ipol": 2375,
    "pola": 3554,
    "sí": 4217,
    " sí": 529,
    "sí ": 4218,
    " sí ": 530,
    "upu": 4581,
    "supu": 4212,
    "upue": 4582,
    "corr": 1257,
    "orre": 3403,
    "rrec": 3881,
    "rect": 3719,
    "así": 924,
    " así": 56,
    "así ": 925,
    "af": 686,
    " af": 17,
    "afi": 687,
    "fir": 1938,
    "mat": 2776,
    " afi": 18,
    "afir": 688,
    "firm": 1939,
    "irma": 2384,
    "rmat": 3821,
    "mati": 2777,
    " ef": 178,
    " efe": 179,
    "efec": 1568,
    "fect": 1916,
    "ecti": 1544,
    "ert": 1779,
    "iert": 2240,
    "erta": 1780,
    "acu": 660,
    "rdo": 3701,
    " acu": 12,
    "acue": 661,
    "uerd": 4495,
    "erdo": 1746,
    "rdo ": 3702,
    "tot": 4359,
    " tot": 551,
    "tota": 4360,
    "otal": 3428,
    "dab": 1336,
    "indu": 2320,
    "ndud": 2971,
    "udab": 4460,
    "dabl": 1337,
    "leme": 2596,
    "utam": 4620,
    "erto": 1781,
    "nfir": 2998,
    "irmo": 2386,
    "ader": 674,
    "cert": 1156,
    "rtad": 3904,
    "coi": 1234,
    "oin": 3251,
    " coi": 114,
    "coin": 1235,
    "oinc": 3252,
    "ncid": 2942,
    "oncu": 3321,
    " ase": 54,
    "aseg": 905,
    "rmar": 3820,
    "marl": 2769,
    "fav": 1911,
    "avo": 958,
    "vor": 4728,
    " fav": 225,
    "favo": 1912,
    "avor": 959,
    "vor ": 4729,
    "úa": 4942,
    "inú": 2353,
    "núa": 3174,
    "úa ": 4943,
    "tinú": 4325,
    "inúa": 2354,
    "núa ": 3175,
    "tarí": 4256,
    "seo ": 4036,
    "ref": 3723,
    "pref": 3575,
    "refi": 3724,
    "efie": 1571,
    "fier": 1932,
    "tere": 4283,
    "esa ": 1791,
    "oce": 3201,
    "ced": 1140,
    "roce": 3845,
    "oced": 3202,
    "cede": 1141,
    "ede ": 1555,
    "zl": 4807,
    "azl": 972,
    "zlo": 4808,
    " haz": 270,
    "hazl": 2094,
    "azlo": 973,
    "zlo ": 4809,
    "yú": 4787,
    "úd": 4944,
    "ayú": 967,
    "yúd": 4788,
    "úda": 4945,
    " ayú": 66,
    "ayúd": 968,
    "yúda": 4789,
    "údam": 4946,
    "nun": 3149,
    " nun": 404,
    "nunc": 3150,
    "unca": 4567,
    "nca ": 2933,
    "luto": 2719,
    " ja": 312,
    "jam": 2486,
    "amá": 786,
    " jam": 313,
    "jamá": 2487,
    "amás": 787,
    "als": 758,
    "lso": 2693,
    "fals": 1903,
    "also": 759,
    "lso ": 2694,
    "epo": 1721,
    "iscr": 2401,
    "scre": 4006,
    "crep": 1272,
    "repo": 3748,
    "epo ": 1722,
    " eq": 196,
    "uiv": 4529,
    "voc": 4724,
    " equ": 197,
    "equi": 1729,
    "quiv": 3631,
    "uivo": 4530,
    "ivoc": 2460,
    "voca": 4725,
    "ocas": 3200,
    "cas ": 1126,
    "cad": 1100,
    "ocad": 3199,
    "cado": 1101,
    "ieg": 2221,
    " nie": 392,
    "nieg": 3023,
    "iego": 2222,
    "iam": 2156,
    "cesa": 1159,
    "sari": 3993,
    "riam": 3781,
    "iame": 2157,
    " ref": 476,
    "bus": 1088,
    " bus": 89,
    "busc": 1089,
    "usco": 4598,
    "sco ": 4002,
    "ablo": 626,
    "blo ": 1056,
    "venc": 4687,
    "ence": 1658,
    "nce ": 2936,
    "uad": 4428,
    "cuad": 1297,
    "uado": 4429,
    "nua": 3139,
    "uar": 4437,
    "tinu": 4324,
    "inua": 2346,
    "nuar": 3140,
    "uar ": 4438,
    " sig": 512,
    "siga": 4077
  },
  "response": null,
  "action_text": null
}